Workbook

Sheet Read me
A1: EMEA Sales Operations Toolkit (demo workbook)
A2: All accounts, people and figures are fictional and generated for demonstration.
A4: Opportunities: raw CRM export with formula-driven data quality checks (columns V to AB).
A5: Pipeline summary: stage x region pivot built with SUMIFS so it updates with the data.
A6: Data quality: completeness score per region, target 95%.
A7: Forecast: forecast vs actual by quarter with accuracy %.
A8: Tradeshows: post-event funnel and cost per qualified lead.

Sheet Opportunities
A1: opportunity_id | B1: account | C1: region | D1: country | E1: owner | F1: vertical | G1: product_family | H1: stage | I1: probability | J1: annual_units | K1: asp_usd | L1: project_life_years | M1: annual_value_usd | N1: lifetime_value_usd | O1: weighted_value_usd | P1: created_date | Q1: expected_close | R1: days_since_update | S1: next_action | T1: source | U1: loss_reason | V1: chk_next_action | W1: chk_volume | X1: chk_vertical | Y1: chk_close_past | Z1: chk_stale | AA1: chk_duplicate | AB1: issues
A2: OPP-26000 | B2: Sava Electronics | C2: UK & Ireland | D2: United Kingdom | E2: R. Patel | F2: Industrial IoT | G2: LTE Cat 1 bis | H2: Pilot | I2: 0.85 | J2: 20000 | K2: 10.24 | L2: 3 | M2: 204800 | N2: 614400 | O2: 522240 | P2: 2025-12-31 | Q2: 2026-11-30 | R2: 79 | S2: Certification plan | T2: Website | V2: =IF(S2="",1,0) | W2: =IF(J2="",1,0) | X2: =IF(F2="",1,0) | Y2: =IF(AND(AND(H2<>"Mass production",H2<>"Lost"),DATEVALUE(Q2)<DATE(2026,10,20)),1,0) | Z2: =IF(AND(AND(H2<>"Mass production",H2<>"Lost"),R2>30),1,0) | AA2: =IF(COUNTIFS($G$2:$G$247,G2,$F$2:$F$247,F2,$J$2:$J$247,J2,$K$2:$K$247,K2)>1,1,0) | AB2: =SUM(V2:AA2)
A3: OPP-26001 | B3: Nordwind Connect | C3: UK & Ireland | D3: United Kingdom | E3: R. Patel | F3: Healthcare | G3: Wi-Fi / Bluetooth | H3: Mass production | I3: 1 | J3: 2000 | K3: 3.3 | L3: 3 | M3: 6600 | N3: 19800 | O3: 19800 | P3: 2025-08-18 | Q3: 2026-06-02 | R3: 13 | S3: Send samples | T3: Direct | V3: =IF(S3="",1,0) | W3: =IF(J3="",1,0) | X3: =IF(F3="",1,0) | Y3: =IF(AND(AND(H3<>"Mass production",H3<>"Lost"),DATEVALUE(Q3)<DATE(2026,10,20)),1,0) | Z3: =IF(AND(AND(H3<>"Mass production",H3<>"Lost"),R3>30),1,0) | AA3: =IF(COUNTIFS($G$2:$G$247,G3,$F$2:$F$247,F3,$J$2:$J$247,J3,$K$2:$K$247,K3)>1,1,0) | AB3: =SUM(V3:AA3)
A4: OPP-26002 | B4: Sava Electronics | C4: UK & Ireland | D4: United Kingdom | E4: S. Clarke | F4: POS & payments | G4: LTE Cat 1 bis | H4: Design-win | I4: 0.7 | J4: 80000 | K4: 7.63 | L4: 4 | M4: 610400 | N4: 2441600 | O4: 1709120 | P4: 2025-10-12 | Q4: 2027-02-17 | R4: 80 | T4: Tradeshow | V4: =IF(S4="",1,0) | W4: =IF(J4="",1,0) | X4: =IF(F4="",1,0) | Y4: =IF(AND(AND(H4<>"Mass production",H4<>"Lost"),DATEVALUE(Q4)<DATE(2026,10,20)),1,0) | Z4: =IF(AND(AND(H4<>"Mass production",H4<>"Lost"),R4>30),1,0) | AA4: =IF(COUNTIFS($G$2:$G$247,G4,$F$2:$F$247,F4,$J$2:$J$247,J4,$K$2:$K$247,K4)>1,1,0) | AB4: =SUM(V4:AA4)
A5: OPP-26003 | B5: Ferro Metering | C5: Middle East & Africa | D5: Israel | E5: Y. Cohen | F5: POS & payments | G5: Smart module | H5: Design-win | I5: 0.7 | J5: 8000 | K5: 81.85 | L5: 3 | M5: 654800 | N5: 1964400 | O5: 1375080 | P5: 2025-07-16 | Q5: 2026-10-15 | R5: 10 | S5: Pilot build follow-up | T5: Tradeshow | V5: =IF(S5="",1,0) | W5: =IF(J5="",1,0) | X5: =IF(F5="",1,0) | Y5: =IF(AND(AND(H5<>"Mass production",H5<>"Lost"),DATEVALUE(Q5)<DATE(2026,10,20)),1,0) | Z5: =IF(AND(AND(H5<>"Mass production",H5<>"Lost"),R5>30),1,0) | AA5: =IF(COUNTIFS($G$2:$G$247,G5,$F$2:$F$247,F5,$J$2:$J$247,J5,$K$2:$K$247,K5)>1,1,0) | AB5: =SUM(V5:AA5)
A6: OPP-26004 | B6: Morava Systems | C6: France & Benelux | D6: Netherlands | E6: B. de Vries | F6: Healthcare | G6: 5G eMBB | H6: Sample / Evaluation | I6: 0.2 | J6: 20000 | K6: 95.55 | L6: 3 | M6: 1911000 | N6: 5733000 | O6: 1146600 | P6: 2025-02-25 | Q6: 2027-02-11 | R6: 6 | S6: Price negotiation | T6: Distributor | V6: =IF(S6="",1,0) | W6: =IF(J6="",1,0) | X6: =IF(F6="",1,0) | Y6: =IF(AND(AND(H6<>"Mass production",H6<>"Lost"),DATEVALUE(Q6)<DATE(2026,10,20)),1,0) | Z6: =IF(AND(AND(H6<>"Mass production",H6<>"Lost"),R6>30),1,0) | AA6: =IF(COUNTIFS($G$2:$G$247,G6,$F$2:$F$247,F6,$J$2:$J$247,J6,$K$2:$K$247,K6)>1,1,0) | AB6: =SUM(V6:AA6)
A7: OPP-26005 | B7: Stellar Devices | C7: UK & Ireland | D7: United Kingdom | E7: S. Clarke | F7: POS & payments | G7: Wi-Fi / Bluetooth | H7: Design-in | I7: 0.4 | J7: 3000 | K7: 5.08 | L7: 3 | M7: 15240 | N7: 45720 | O7: 18288 | P7: 2025-04-21 | Q7: 2026-10-05 | R7: 25 | S7: Certification plan | T7: Website | V7: =IF(S7="",1,0) | W7: =IF(J7="",1,0) | X7: =IF(F7="",1,0) | Y7: =IF(AND(AND(H7<>"Mass production",H7<>"Lost"),DATEVALUE(Q7)<DATE(2026,10,20)),1,0) | Z7: =IF(AND(AND(H7<>"Mass production",H7<>"Lost"),R7>30),1,0) | AA7: =IF(COUNTIFS($G$2:$G$247,G7,$F$2:$F$247,F7,$J$2:$J$247,J7,$K$2:$K$247,K7)>1,1,0) | AB7: =SUM(V7:AA7)
A8: OPP-26006 | B8: Atlas Industrial | C8: France & Benelux | D8: Belgium | E8: C. Martin | G8: GNSS | H8: Lost | I8: 0 | J8: 3000 | K8: 8.17 | L8: 4 | M8: 24510 | N8: 98040 | O8: 0 | P8: 2025-08-02 | Q8: 2026-09-20 | R8: 11 | S8: Technical review call | T8: Tradeshow | U8: Competitor module | V8: =IF(S8="",1,0) | W8: =IF(J8="",1,0) | X8: =IF(F8="",1,0) | Y8: =IF(AND(AND(H8<>"Mass production",H8<>"Lost"),DATEVALUE(Q8)<DATE(2026,10,20)),1,0) | Z8: =IF(AND(AND(H8<>"Mass production",H8<>"Lost"),R8>30),1,0) | AA8: =IF(COUNTIFS($G$2:$G$247,G8,$F$2:$F$247,F8,$J$2:$J$247,J8,$K$2:$K$247,K8)>1,1,0) | AB8: =SUM(V8:AA8)
A9: OPP-26007 | B9: Morava Systems | C9: France & Benelux | D9: Netherlands | E9: B. de Vries | F9: Telematics | G9: 5G RedCap | H9: Design-in | I9: 0.4 | J9: 3000 | K9: 51.38 | L9: 4 | M9: 154140 | N9: 616560 | O9: 246624 | P9: 2026-05-17 | Q9: 2027-05-05 | R9: 25 | S9: Quote revision | T9: Tradeshow | V9: =IF(S9="",1,0) | W9: =IF(J9="",1,0) | X9: =IF(F9="",1,0) | Y9: =IF(AND(AND(H9<>"Mass production",H9<>"Lost"),DATEVALUE(Q9)<DATE(2026,10,20)),1,0) | Z9: =IF(AND(AND(H9<>"Mass production",H9<>"Lost"),R9>30),1,0) | AA9: =IF(COUNTIFS($G$2:$G$247,G9,$F$2:$F$247,F9,$J$2:$J$247,J9,$K$2:$K$247,K9)>1,1,0) | AB9: =SUM(V9:AA9)
A10: OPP-26008 | B10: Rhenus Tracking | C10: UK & Ireland | D10: Ireland | E10: R. Patel | F10: Healthcare | G10: Wi-Fi / Bluetooth | H10: Pilot | I10: 0.85 | J10: 50000 | K10: 4.73 | L10: 4 | M10: 236500 | N10: 946000 | O10: 804100 | P10: 2026-01-29 | Q10: 2027-01-28 | R10: 7 | S10: Technical review call | T10: Direct | V10: =IF(S10="",1,0) | W10: =IF(J10="",1,0) | X10: =IF(F10="",1,0) | Y10: =IF(AND(AND(H10<>"Mass production",H10<>"Lost"),DATEVALUE(Q10)<DATE(2026,10,20)),1,0) | Z10: =IF(AND(AND(H10<>"Mass production",H10<>"Lost"),R10>30),1,0) | AA10: =IF(COUNTIFS($G$2:$G$247,G10,$F$2:$F$247,F10,$J$2:$J$247,J10,$K$2:$K$247,K10)>1,1,0) | AB10: =SUM(V10:AA10)
A11: OPP-26009 | B11: Corvid Health | C11: DACH | D11: Germany | E11: L. Hoffmann | F11: Smart metering | G11: 5G eMBB | H11: Qualified | I11: 0.1 | J11: 20000 | K11: 88.53 | L11: 3 | M11: 1770600 | N11: 5311800 | O11: 531180 | P11: 2025-03-24 | Q11: 2027-05-06 | R11: 57 | S11: Design review | T11: Distributor | V11: =IF(S11="",1,0) | W11: =IF(J11="",1,0) | X11: =IF(F11="",1,0) | Y11: =IF(AND(AND(H11<>"Mass production",H11<>"Lost"),DATEVALUE(Q11)<DATE(2026,10,20)),1,0) | Z11: =IF(AND(AND(H11<>"Mass production",H11<>"Lost"),R11>30),1,0) | AA11: =IF(COUNTIFS($G$2:$G$247,G11,$F$2:$F$247,F11,$J$2:$J$247,J11,$K$2:$K$247,K11)>1,1,0) | AB11: =SUM(V11:AA11)
A12: OPP-26010 | B12: Orbis Systems | C12: France & Benelux | D12: Belgium | E12: C. Martin | F12: Smart home & security | G12: Wi-Fi / Bluetooth | H12: Pilot | I12: 0.85 | J12: 20000 | K12: 5.62 | L12: 5 | M12: 112400 | N12: 562000 | O12: 477700 | P12: 2025-03-20 | Q12: 2026-12-31 | R12: 7 | S12: Forecast confirmation | T12: Tradeshow | V12: =IF(S12="",1,0) | W12: =IF(J12="",1,0) | X12: =IF(F12="",1,0) | Y12: =IF(AND(AND(H12<>"Mass production",H12<>"Lost"),DATEVALUE(Q12)<DATE(2026,10,20)),1,0) | Z12: =IF(AND(AND(H12<>"Mass production",H12<>"Lost"),R12>30),1,0) | AA12: =IF(COUNTIFS($G$2:$G$247,G12,$F$2:$F$247,F12,$J$2:$J$247,J12,$K$2:$K$247,K12)>1,1,0) | AB12: =SUM(V12:AA12)
A13: OPP-26011 | B13: Zenit Telematics | C13: UK & Ireland | D13: Ireland | E13: S. Clarke | F13: Telematics | G13: LTE-M / NB-IoT | H13: Qualified | I13: 0.1 | J13: 80000 | K13: 8.26 | L13: 5 | M13: 660800 | N13: 3304000 | O13: 330400 | P13: 2026-09-03 | Q13: 2027-03-30 | R13: 15 | S13: Quote revision | T13: Direct | V13: =IF(S13="",1,0) | W13: =IF(J13="",1,0) | X13: =IF(F13="",1,0) | Y13: =IF(AND(AND(H13<>"Mass production",H13<>"Lost"),DATEVALUE(Q13)<DATE(2026,10,20)),1,0) | Z13: =IF(AND(AND(H13<>"Mass production",H13<>"Lost"),R13>30),1,0) | AA13: =IF(COUNTIFS($G$2:$G$247,G13,$F$2:$F$247,F13,$J$2:$J$247,J13,$K$2:$K$247,K13)>1,1,0) | AB13: =SUM(V13:AA13)
A14: OPP-26012 | B14: Orbis Devices | C14: Middle East & Africa | D14: UAE | E14: Y. Cohen | F14: Healthcare | G14: LTE Cat 1 bis | H14: Design-in | I14: 0.4 | J14: 20000 | K14: 10.16 | L14: 3 | M14: 203200 | N14: 609600 | O14: 243840 | P14: 2025-07-26 | Q14: 2027-01-17 | R14: 13 | S14: Certification plan | T14: Tradeshow | V14: =IF(S14="",1,0) | W14: =IF(J14="",1,0) | X14: =IF(F14="",1,0) | Y14: =IF(AND(AND(H14<>"Mass production",H14<>"Lost"),DATEVALUE(Q14)<DATE(2026,10,20)),1,0) | Z14: =IF(AND(AND(H14<>"Mass production",H14<>"Lost"),R14>30),1,0) | AA14: =IF(COUNTIFS($G$2:$G$247,G14,$F$2:$F$247,F14,$J$2:$J$247,J14,$K$2:$K$247,K14)>1,1,0) | AB14: =SUM(V14:AA14)
A15: OPP-26013 | B15: Lumen Connect | C15: DACH | D15: Austria | E15: J. Weber | G15: 5G RedCap | H15: Lead | I15: 0.05 | J15: 8000 | K15: 60.79 | L15: 2 | M15: 486320 | N15: 972640 | O15: 48632 | P15: 2026-04-27 | Q15: 2027-01-10 | R15: 2 | S15: Pilot build follow-up | T15: Tradeshow | V15: =IF(S15="",1,0) | W15: =IF(J15="",1,0) | X15: =IF(F15="",1,0) | Y15: =IF(AND(AND(H15<>"Mass production",H15<>"Lost"),DATEVALUE(Q15)<DATE(2026,10,20)),1,0) | Z15: =IF(AND(AND(H15<>"Mass production",H15<>"Lost"),R15>30),1,0) | AA15: =IF(COUNTIFS($G$2:$G$247,G15,$F$2:$F$247,F15,$J$2:$J$247,J15,$K$2:$K$247,K15)>1,1,0) | AB15: =SUM(V15:AA15)
A16: OPP-26014 | B16: Baltix Telematics | C16: DACH | D16: Germany | E16: L. Hoffmann | F16: Smart home & security | G16: Smart module | H16: Lost | I16: 0 | K16: 50.73 | L16: 3 | M16: 0 | N16: 0 | O16: 0 | P16: 2026-06-12 | Q16: 2026-10-19 | R16: 24 | S16: Certification plan | T16: Direct | U16: Competitor module | V16: =IF(S16="",1,0) | W16: =IF(J16="",1,0) | X16: =IF(F16="",1,0) | Y16: =IF(AND(AND(H16<>"Mass production",H16<>"Lost"),DATEVALUE(Q16)<DATE(2026,10,20)),1,0) | Z16: =IF(AND(AND(H16<>"Mass production",H16<>"Lost"),R16>30),1,0) | AA16: =IF(COUNTIFS($G$2:$G$247,G16,$F$2:$F$247,F16,$J$2:$J$247,J16,$K$2:$K$247,K16)>1,1,0) | AB16: =SUM(V16:AA16)
A17: OPP-26015 | B17: Orbis Systems | C17: France & Benelux | D17: Belgium | E17: B. de Vries | F17: Smart metering | G17: GNSS | H17: Mass production | I17: 1 | K17: 7.93 | L17: 2 | M17: 0 | N17: 0 | O17: 0 | P17: 2025-10-10 | Q17: 2026-10-06 | R17: 10 | S17: Design review | T17: Website | V17: =IF(S17="",1,0) | W17: =IF(J17="",1,0) | X17: =IF(F17="",1,0) | Y17: =IF(AND(AND(H17<>"Mass production",H17<>"Lost"),DATEVALUE(Q17)<DATE(2026,10,20)),1,0) | Z17: =IF(AND(AND(H17<>"Mass production",H17<>"Lost"),R17>30),1,0) | AA17: =IF(COUNTIFS($G$2:$G$247,G17,$F$2:$F$247,F17,$J$2:$J$247,J17,$K$2:$K$247,K17)>1,1,0) | AB17: =SUM(V17:AA17)
A18: OPP-26016 | B18: Helix Health | C18: Nordics | D18: Finland | E18: E. Lindqvist | F18: Telematics | G18: Wi-Fi / Bluetooth | H18: Design-win | I18: 0.7 | J18: 5000 | K18: 4.11 | L18: 4 | M18: 20550 | N18: 82200 | O18: 57540 | P18: 2026-04-03 | Q18: 2027-06-04 | R18: 23 | S18: Design review | T18: Website | V18: =IF(S18="",1,0) | W18: =IF(J18="",1,0) | X18: =IF(F18="",1,0) | Y18: =IF(AND(AND(H18<>"Mass production",H18<>"Lost"),DATEVALUE(Q18)<DATE(2026,10,20)),1,0) | Z18: =IF(AND(AND(H18<>"Mass production",H18<>"Lost"),R18>30),1,0) | AA18: =IF(COUNTIFS($G$2:$G$247,G18,$F$2:$F$247,F18,$J$2:$J$247,J18,$K$2:$K$247,K18)>1,1,0) | AB18: =SUM(V18:AA18)
A19: OPP-26017 | B19: Arcturus Metering | C19: DACH | D19: Switzerland | E19: L. Hoffmann | F19: Asset tracking | G19: Wi-Fi / Bluetooth | H19: Mass production | I19: 1 | J19: 10000 | K19: 5.77 | L19: 4 | M19: 57700 | N19: 230800 | O19: 230800 | P19: 2026-01-24 | Q19: 2026-10-01 | R19: 9 | S19: Price negotiation | T19: Direct | V19: =IF(S19="",1,0) | W19: =IF(J19="",1,0) | X19: =IF(F19="",1,0) | Y19: =IF(AND(AND(H19<>"Mass production",H19<>"Lost"),DATEVALUE(Q19)<DATE(2026,10,20)),1,0) | Z19: =IF(AND(AND(H19<>"Mass production",H19<>"Lost"),R19>30),1,0) | AA19: =IF(COUNTIFS($G$2:$G$247,G19,$F$2:$F$247,F19,$J$2:$J$247,J19,$K$2:$K$247,K19)>1,1,0) | AB19: =SUM(V19:AA19)
A20: OPP-26018 | B20: Rhenus Health | C20: Nordics | D20: Finland | E20: E. Lindqvist | F20: Industrial IoT | G20: GNSS | H20: Sample / Evaluation | I20: 0.2 | J20: 10000 | K20: 7.36 | L20: 5 | M20: 73600 | N20: 368000 | O20: 73600 | P20: 2026-09-20 | Q20: 2027-06-01 | R20: 17 | S20: Price negotiation | T20: Tradeshow | V20: =IF(S20="",1,0) | W20: =IF(J20="",1,0) | X20: =IF(F20="",1,0) | Y20: =IF(AND(AND(H20<>"Mass production",H20<>"Lost"),DATEVALUE(Q20)<DATE(2026,10,20)),1,0) | Z20: =IF(AND(AND(H20<>"Mass production",H20<>"Lost"),R20>30),1,0) | AA20: =IF(COUNTIFS($G$2:$G$247,G20,$F$2:$F$247,F20,$J$2:$J$247,J20,$K$2:$K$247,K20)>1,1,0) | AB20: =SUM(V20:AA20)
A21: OPP-26019 | B21: Zenit Energy | C21: CEE | D21: Poland | E21: D. Jovanovic | F21: Healthcare | G21: 5G eMBB | H21: Lead | I21: 0.05 | J21: 8000 | K21: 107.24 | L21: 3 | M21: 857920 | N21: 2573760 | O21: 128688 | P21: 2025-02-12 | Q21: 2027-03-17 | R21: 85 | S21: Price negotiation | T21: Direct | V21: =IF(S21="",1,0) | W21: =IF(J21="",1,0) | X21: =IF(F21="",1,0) | Y21: =IF(AND(AND(H21<>"Mass production",H21<>"Lost"),DATEVALUE(Q21)<DATE(2026,10,20)),1,0) | Z21: =IF(AND(AND(H21<>"Mass production",H21<>"Lost"),R21>30),1,0) | AA21: =IF(COUNTIFS($G$2:$G$247,G21,$F$2:$F$247,F21,$J$2:$J$247,J21,$K$2:$K$247,K21)>1,1,0) | AB21: =SUM(V21:AA21)
A22: OPP-26020 | B22: Arcturus Telematics | C22: UK & Ireland | D22: Ireland | E22: R. Patel | F22: Automotive & C-V2X | G22: LTE Cat 1 bis | H22: Pilot | I22: 0.85 | J22: 50000 | K22: 7.92 | L22: 3 | M22: 396000 | N22: 1188000 | O22: 1009800 | P22: 2026-03-18 | Q22: 2026-12-29 | R22: 30 | S22: Certification plan | T22: Direct | V22: =IF(S22="",1,0) | W22: =IF(J22="",1,0) | X22: =IF(F22="",1,0) | Y22: =IF(AND(AND(H22<>"Mass production",H22<>"Lost"),DATEVALUE(Q22)<DATE(2026,10,20)),1,0) | Z22: =IF(AND(AND(H22<>"Mass production",H22<>"Lost"),R22>30),1,0) | AA22: =IF(COUNTIFS($G$2:$G$247,G22,$F$2:$F$247,F22,$J$2:$J$247,J22,$K$2:$K$247,K22)>1,1,0) | AB22: =SUM(V22:AA22)
A23: OPP-26021 | B23: Orbis Systems | C23: France & Benelux | D23: Belgium | E23: B. de Vries | F23: Automotive & C-V2X | G23: GNSS | H23: Lead | I23: 0.05 | J23: 2000 | K23: 4.2 | L23: 2 | M23: 8400 | N23: 16800 | O23: 840 | P23: 2025-03-13 | Q23: 2027-02-06 | R23: 112 | S23: Send samples | T23: Distributor | V23: =IF(S23="",1,0) | W23: =IF(J23="",1,0) | X23: =IF(F23="",1,0) | Y23: =IF(AND(AND(H23<>"Mass production",H23<>"Lost"),DATEVALUE(Q23)<DATE(2026,10,20)),1,0) | Z23: =IF(AND(AND(H23<>"Mass production",H23<>"Lost"),R23>30),1,0) | AA23: =IF(COUNTIFS($G$2:$G$247,G23,$F$2:$F$247,F23,$J$2:$J$247,J23,$K$2:$K$247,K23)>1,1,0) | AB23: =SUM(V23:AA23)
A24: OPP-26022 | B24: Pannon Energy | C24: DACH | D24: Switzerland | E24: J. Weber | F24: Asset tracking | G24: 5G RedCap | H24: Sample / Evaluation | I24: 0.2 | J24: 30000 | K24: 44.06 | L24: 2 | M24: 1321800 | N24: 2643600 | O24: 528720 | P24: 2026-07-26 | Q24: 2027-04-03 | R24: 17 | S24: Quote revision | T24: Website | V24: =IF(S24="",1,0) | W24: =IF(J24="",1,0) | X24: =IF(F24="",1,0) | Y24: =IF(AND(AND(H24<>"Mass production",H24<>"Lost"),DATEVALUE(Q24)<DATE(2026,10,20)),1,0) | Z24: =IF(AND(AND(H24<>"Mass production",H24<>"Lost"),R24>30),1,0) | AA24: =IF(COUNTIFS($G$2:$G$247,G24,$F$2:$F$247,F24,$J$2:$J$247,J24,$K$2:$K$247,K24)>1,1,0) | AB24: =SUM(V24:AA24)
A25: OPP-26023 | B25: Orbis Connect | C25: UK & Ireland | D25: United Kingdom | E25: R. Patel | F25: Smart home & security | G25: 5G RedCap | H25: Lost | I25: 0 | J25: 20000 | K25: 51.39 | L25: 5 | M25: 1027800 | N25: 5139000 | O25: 0 | P25: 2025-01-28 | Q25: 2025-09-20 | R25: 88 | S25: Pilot build follow-up | T25: Distributor | U25: Price | V25: =IF(S25="",1,0) | W25: =IF(J25="",1,0) | X25: =IF(F25="",1,0) | Y25: =IF(AND(AND(H25<>"Mass production",H25<>"Lost"),DATEVALUE(Q25)<DATE(2026,10,20)),1,0) | Z25: =IF(AND(AND(H25<>"Mass production",H25<>"Lost"),R25>30),1,0) | AA25: =IF(COUNTIFS($G$2:$G$247,G25,$F$2:$F$247,F25,$J$2:$J$247,J25,$K$2:$K$247,K25)>1,1,0) | AB25: =SUM(V25:AA25)
A26: OPP-26024 | B26: Ferro Systems | C26: CEE | D26: Poland | E26: K. Nowak | F26: Smart home & security | G26: Wi-Fi / Bluetooth | H26: Lead | I26: 0.05 | J26: 8000 | K26: 3.23 | L26: 3 | M26: 25840 | N26: 77520 | O26: 3876 | P26: 2026-07-09 | Q26: 2026-11-29 | R26: 3 | S26: Price negotiation | T26: Tradeshow | V26: =IF(S26="",1,0) | W26: =IF(J26="",1,0) | X26: =IF(F26="",1,0) | Y26: =IF(AND(AND(H26<>"Mass production",H26<>"Lost"),DATEVALUE(Q26)<DATE(2026,10,20)),1,0) | Z26: =IF(AND(AND(H26<>"Mass production",H26<>"Lost"),R26>30),1,0) | AA26: =IF(COUNTIFS($G$2:$G$247,G26,$F$2:$F$247,F26,$J$2:$J$247,J26,$K$2:$K$247,K26)>1,1,0) | AB26: =SUM(V26:AA26)
A27: OPP-26025 | B27: Helix Devices | C27: France & Benelux | D27: France | E27: C. Martin | F27: Asset tracking | G27: Smart module | H27: Qualified | I27: 0.1 | K27: 59.14 | L27: 2 | M27: 0 | N27: 0 | O27: 0 | P27: 2026-02-03 | Q27: 2027-01-23 | R27: 12 | S27: Pilot build follow-up | T27: Website | V27: =IF(S27="",1,0) | W27: =IF(J27="",1,0) | X27: =IF(F27="",1,0) | Y27: =IF(AND(AND(H27<>"Mass production",H27<>"Lost"),DATEVALUE(Q27)<DATE(2026,10,20)),1,0) | Z27: =IF(AND(AND(H27<>"Mass production",H27<>"Lost"),R27>30),1,0) | AA27: =IF(COUNTIFS($G$2:$G$247,G27,$F$2:$F$247,F27,$J$2:$J$247,J27,$K$2:$K$247,K27)>1,1,0) | AB27: =SUM(V27:AA27)
A28: OPP-26026 | B28: Vector Metering | C28: DACH | D28: Germany | E28: L. Hoffmann | F28: Telematics | G28: GNSS | H28: Mass production | I28: 1 | J28: 80000 | K28: 7.62 | L28: 3 | M28: 609600 | N28: 1828800 | O28: 1828800 | P28: 2025-07-08 | Q28: 2026-01-07 | R28: 11 | T28: Direct | V28: =IF(S28="",1,0) | W28: =IF(J28="",1,0) | X28: =IF(F28="",1,0) | Y28: =IF(AND(AND(H28<>"Mass production",H28<>"Lost"),DATEVALUE(Q28)<DATE(2026,10,20)),1,0) | Z28: =IF(AND(AND(H28<>"Mass production",H28<>"Lost"),R28>30),1,0) | AA28: =IF(COUNTIFS($G$2:$G$247,G28,$F$2:$F$247,F28,$J$2:$J$247,J28,$K$2:$K$247,K28)>1,1,0) | AB28: =SUM(V28:AA28)
A29: OPP-26027 | B29: Zenit Labs | C29: UK & Ireland | D29: Ireland | E29: S. Clarke | G29: GNSS | H29: Pilot | I29: 0.85 | J29: 3000 | K29: 4.88 | L29: 3 | M29: 14640 | N29: 43920 | O29: 37332 | P29: 2025-02-18 | Q29: 2026-09-20 | R29: 12 | S29: Price negotiation | T29: FAE referral | V29: =IF(S29="",1,0) | W29: =IF(J29="",1,0) | X29: =IF(F29="",1,0) | Y29: =IF(AND(AND(H29<>"Mass production",H29<>"Lost"),DATEVALUE(Q29)<DATE(2026,10,20)),1,0) | Z29: =IF(AND(AND(H29<>"Mass production",H29<>"Lost"),R29>30),1,0) | AA29: =IF(COUNTIFS($G$2:$G$247,G29,$F$2:$F$247,F29,$J$2:$J$247,J29,$K$2:$K$247,K29)>1,1,0) | AB29: =SUM(V29:AA29)
A30: OPP-26028 | B30: Vector Devices | C30: UK & Ireland | D30: United Kingdom | E30: S. Clarke | F30: Healthcare | G30: Wi-Fi / Bluetooth | H30: Design-in | I30: 0.4 | J30: 3000 | K30: 4.22 | L30: 4 | M30: 12660 | N30: 50640 | O30: 20256 | P30: 2025-10-09 | Q30: 2027-04-07 | R30: 5 | S30: Design review | T30: Tradeshow | V30: =IF(S30="",1,0) | W30: =IF(J30="",1,0) | X30: =IF(F30="",1,0) | Y30: =IF(AND(AND(H30<>"Mass production",H30<>"Lost"),DATEVALUE(Q30)<DATE(2026,10,20)),1,0) | Z30: =IF(AND(AND(H30<>"Mass production",H30<>"Lost"),R30>30),1,0) | AA30: =IF(COUNTIFS($G$2:$G$247,G30,$F$2:$F$247,F30,$J$2:$J$247,J30,$K$2:$K$247,K30)>1,1,0) | AB30: =SUM(V30:AA30)
A31: OPP-26029 | B31: Alpenlink Electronics | C31: DACH | D31: Germany | E31: J. Weber | F31: Telematics | G31: GNSS | H31: Mass production | I31: 1 | J31: 3000 | K31: 3.7 | L31: 3 | M31: 11100 | N31: 33300 | O31: 33300 | P31: 2026-01-15 | Q31: 2026-10-16 | R31: 96 | S31: Design review | T31: Direct | V31: =IF(S31="",1,0) | W31: =IF(J31="",1,0) | X31: =IF(F31="",1,0) | Y31: =IF(AND(AND(H31<>"Mass production",H31<>"Lost"),DATEVALUE(Q31)<DATE(2026,10,20)),1,0) | Z31: =IF(AND(AND(H31<>"Mass production",H31<>"Lost"),R31>30),1,0) | AA31: =IF(COUNTIFS($G$2:$G$247,G31,$F$2:$F$247,F31,$J$2:$J$247,J31,$K$2:$K$247,K31)>1,1,0) | AB31: =SUM(V31:AA31)
A32: OPP-26030 | B32: Bluecell Devices | C32: UK & Ireland | D32: United Kingdom | E32: R. Patel | F32: Automotive & C-V2X | G32: Smart module | H32: Pilot | I32: 0.85 | J32: 2000 | K32: 67.1 | L32: 3 | M32: 134200 | N32: 402600 | O32: 342210 | P32: 2025-12-31 | Q32: 2026-11-16 | R32: 87 | S32: Send samples | T32: FAE referral | V32: =IF(S32="",1,0) | W32: =IF(J32="",1,0) | X32: =IF(F32="",1,0) | Y32: =IF(AND(AND(H32<>"Mass production",H32<>"Lost"),DATEVALUE(Q32)<DATE(2026,10,20)),1,0) | Z32: =IF(AND(AND(H32<>"Mass production",H32<>"Lost"),R32>30),1,0) | AA32: =IF(COUNTIFS($G$2:$G$247,G32,$F$2:$F$247,F32,$J$2:$J$247,J32,$K$2:$K$247,K32)>1,1,0) | AB32: =SUM(V32:AA32)
A33: OPP-26031 | B33: Corvid Connect | C33: DACH | D33: Austria | E33: J. Weber | F33: Telematics | G33: LTE Cat 1 bis | H33: Pilot | I33: 0.85 | J33: 50000 | K33: 9.43 | L33: 4 | M33: 471500 | N33: 1886000 | O33: 1603100 | P33: 2026-06-27 | Q33: 2027-01-03 | R33: 90 | S33: Pilot build follow-up | T33: Distributor | V33: =IF(S33="",1,0) | W33: =IF(J33="",1,0) | X33: =IF(F33="",1,0) | Y33: =IF(AND(AND(H33<>"Mass production",H33<>"Lost"),DATEVALUE(Q33)<DATE(2026,10,20)),1,0) | Z33: =IF(AND(AND(H33<>"Mass production",H33<>"Lost"),R33>30),1,0) | AA33: =IF(COUNTIFS($G$2:$G$247,G33,$F$2:$F$247,F33,$J$2:$J$247,J33,$K$2:$K$247,K33)>1,1,0) | AB33: =SUM(V33:AA33)
A34: OPP-26032 | B34: Rhenus Devices | C34: DACH | D34: Austria | E34: L. Hoffmann | F34: Healthcare | G34: 5G eMBB | H34: Lost | I34: 0 | J34: 5000 | K34: 110.12 | L34: 4 | M34: 550600 | N34: 2202400 | O34: 0 | P34: 2026-03-19 | Q34: 2026-09-26 | R34: 14 | S34: Pilot build follow-up | T34: Website | U34: Project cancelled | V34: =IF(S34="",1,0) | W34: =IF(J34="",1,0) | X34: =IF(F34="",1,0) | Y34: =IF(AND(AND(H34<>"Mass production",H34<>"Lost"),DATEVALUE(Q34)<DATE(2026,10,20)),1,0) | Z34: =IF(AND(AND(H34<>"Mass production",H34<>"Lost"),R34>30),1,0) | AA34: =IF(COUNTIFS($G$2:$G$247,G34,$F$2:$F$247,F34,$J$2:$J$247,J34,$K$2:$K$247,K34)>1,1,0) | AB34: =SUM(V34:AA34)
A35: OPP-26033 | B35: Zenit Tracking | C35: UK & Ireland | D35: Ireland | E35: R. Patel | F35: Telematics | G35: Smart module | H35: Design-in | I35: 0.4 | J35: 5000 | K35: 69.48 | L35: 4 | M35: 347400 | N35: 1389600 | O35: 555840 | P35: 2025-03-28 | Q35: 2027-05-15 | R35: 25 | S35: Forecast confirmation | T35: Website | V35: =IF(S35="",1,0) | W35: =IF(J35="",1,0) | X35: =IF(F35="",1,0) | Y35: =IF(AND(AND(H35<>"Mass production",H35<>"Lost"),DATEVALUE(Q35)<DATE(2026,10,20)),1,0) | Z35: =IF(AND(AND(H35<>"Mass production",H35<>"Lost"),R35>30),1,0) | AA35: =IF(COUNTIFS($G$2:$G$247,G35,$F$2:$F$247,F35,$J$2:$J$247,J35,$K$2:$K$247,K35)>1,1,0) | AB35: =SUM(V35:AA35)
A36: OPP-26034 | B36: Corvid Connect | C36: DACH | D36: Austria | E36: J. Weber | F36: Telematics | G36: 5G eMBB | H36: Design-in | I36: 0.4 | J36: 20000 | K36: 132.08 | L36: 2 | M36: 2641600 | N36: 5283200 | O36: 2113280 | P36: 2025-11-09 | Q36: 2027-05-10 | R36: 80 | S36: Send samples | T36: Direct | V36: =IF(S36="",1,0) | W36: =IF(J36="",1,0) | X36: =IF(F36="",1,0) | Y36: =IF(AND(AND(H36<>"Mass production",H36<>"Lost"),DATEVALUE(Q36)<DATE(2026,10,20)),1,0) | Z36: =IF(AND(AND(H36<>"Mass production",H36<>"Lost"),R36>30),1,0) | AA36: =IF(COUNTIFS($G$2:$G$247,G36,$F$2:$F$247,F36,$J$2:$J$247,J36,$K$2:$K$247,K36)>1,1,0) | AB36: =SUM(V36:AA36)
A37: OPP-26035 | B37: Bluecell Telematics | C37: Nordics | D37: Sweden | E37: E. Lindqvist | F37: Telematics | G37: Wi-Fi / Bluetooth | H37: Mass production | I37: 1 | J37: 3000 | K37: 5.46 | L37: 5 | M37: 16380 | N37: 81900 | O37: 81900 | P37: 2025-06-20 | Q37: 2025-10-25 | R37: 114 | S37: Pilot build follow-up | T37: Direct | V37: =IF(S37="",1,0) | W37: =IF(J37="",1,0) | X37: =IF(F37="",1,0) | Y37: =IF(AND(AND(H37<>"Mass production",H37<>"Lost"),DATEVALUE(Q37)<DATE(2026,10,20)),1,0) | Z37: =IF(AND(AND(H37<>"Mass production",H37<>"Lost"),R37>30),1,0) | AA37: =IF(COUNTIFS($G$2:$G$247,G37,$F$2:$F$247,F37,$J$2:$J$247,J37,$K$2:$K$247,K37)>1,1,0) | AB37: =SUM(V37:AA37)
A38: OPP-26036 | B38: Lumen Connect | C38: DACH | D38: Austria | E38: J. Weber | F38: Industrial IoT | G38: LTE Cat 1 bis | H38: Lead | I38: 0.05 | J38: 50000 | K38: 10.48 | L38: 4 | M38: 524000 | N38: 2096000 | O38: 104800 | P38: 2025-11-10 | Q38: 2027-07-27 | R38: 11 | S38: Pilot build follow-up | T38: FAE referral | V38: =IF(S38="",1,0) | W38: =IF(J38="",1,0) | X38: =IF(F38="",1,0) | Y38: =IF(AND(AND(H38<>"Mass production",H38<>"Lost"),DATEVALUE(Q38)<DATE(2026,10,20)),1,0) | Z38: =IF(AND(AND(H38<>"Mass production",H38<>"Lost"),R38>30),1,0) | AA38: =IF(COUNTIFS($G$2:$G$247,G38,$F$2:$F$247,F38,$J$2:$J$247,J38,$K$2:$K$247,K38)>1,1,0) | AB38: =SUM(V38:AA38)
A39: OPP-26037 | B39: Zenit Labs | C39: UK & Ireland | D39: Ireland | E39: R. Patel | F39: Healthcare | G39: Wi-Fi / Bluetooth | H39: Lost | I39: 0 | J39: 3000 | K39: 4.72 | L39: 4 | M39: 14160 | N39: 56640 | O39: 0 | P39: 2026-04-13 | Q39: 2026-09-21 | R39: 16 | S39: Forecast confirmation | T39: Distributor | U39: Competitor module | V39: =IF(S39="",1,0) | W39: =IF(J39="",1,0) | X39: =IF(F39="",1,0) | Y39: =IF(AND(AND(H39<>"Mass production",H39<>"Lost"),DATEVALUE(Q39)<DATE(2026,10,20)),1,0) | Z39: =IF(AND(AND(H39<>"Mass production",H39<>"Lost"),R39>30),1,0) | AA39: =IF(COUNTIFS($G$2:$G$247,G39,$F$2:$F$247,F39,$J$2:$J$247,J39,$K$2:$K$247,K39)>1,1,0) | AB39: =SUM(V39:AA39)
A40: OPP-26038 | B40: Bluecell Labs | C40: Southern Europe | D40: Portugal | E40: A. Garcia | F40: Telematics | G40: 5G eMBB | H40: Design-win | I40: 0.7 | J40: 3000 | K40: 94.35 | L40: 5 | M40: 283050 | N40: 1415250 | O40: 990675 | P40: 2025-09-04 | Q40: 2027-01-11 | R40: 7 | S40: Pilot build follow-up | T40: Tradeshow | V40: =IF(S40="",1,0) | W40: =IF(J40="",1,0) | X40: =IF(F40="",1,0) | Y40: =IF(AND(AND(H40<>"Mass production",H40<>"Lost"),DATEVALUE(Q40)<DATE(2026,10,20)),1,0) | Z40: =IF(AND(AND(H40<>"Mass production",H40<>"Lost"),R40>30),1,0) | AA40: =IF(COUNTIFS($G$2:$G$247,G40,$F$2:$F$247,F40,$J$2:$J$247,J40,$K$2:$K$247,K40)>1,1,0) | AB40: =SUM(V40:AA40)
A41: OPP-26039 | B41: Pannon Devices | C41: CEE | D41: Poland | E41: D. Jovanovic | F41: Industrial IoT | G41: Smart module | H41: Lost | I41: 0 | J41: 3000 | K41: 72.33 | L41: 4 | M41: 216990 | N41: 867960 | O41: 0 | P41: 2025-10-12 | Q41: 2026-10-10 | R41: 10 | S41: Design review | T41: Website | U41: Price | V41: =IF(S41="",1,0) | W41: =IF(J41="",1,0) | X41: =IF(F41="",1,0) | Y41: =IF(AND(AND(H41<>"Mass production",H41<>"Lost"),DATEVALUE(Q41)<DATE(2026,10,20)),1,0) | Z41: =IF(AND(AND(H41<>"Mass production",H41<>"Lost"),R41>30),1,0) | AA41: =IF(COUNTIFS($G$2:$G$247,G41,$F$2:$F$247,F41,$J$2:$J$247,J41,$K$2:$K$247,K41)>1,1,0) | AB41: =SUM(V41:AA41)
A42: OPP-26040 | B42: Iberix Electronics | C42: Middle East & Africa | D42: UAE | E42: O. Demir | F42: Industrial IoT | G42: LTE Cat 1 bis | H42: Sample / Evaluation | I42: 0.2 | J42: 10000 | K42: 10.97 | L42: 2 | M42: 109700 | N42: 219400 | O42: 43880 | P42: 2025-08-21 | Q42: 2027-01-28 | R42: 16 | S42: Forecast confirmation | T42: Direct | V42: =IF(S42="",1,0) | W42: =IF(J42="",1,0) | X42: =IF(F42="",1,0) | Y42: =IF(AND(AND(H42<>"Mass production",H42<>"Lost"),DATEVALUE(Q42)<DATE(2026,10,20)),1,0) | Z42: =IF(AND(AND(H42<>"Mass production",H42<>"Lost"),R42>30),1,0) | AA42: =IF(COUNTIFS($G$2:$G$247,G42,$F$2:$F$247,F42,$J$2:$J$247,J42,$K$2:$K$247,K42)>1,1,0) | AB42: =SUM(V42:AA42)
A43: OPP-26041 | B43: Nordwind Tracking | C43: Nordics | D43: Denmark | E43: E. Lindqvist | F43: Automotive & C-V2X | G43: Smart module | H43: Design-win | I43: 0.7 | J43: 5000 | K43: 83.37 | L43: 2 | M43: 416850 | N43: 833700 | O43: 583590 | P43: 2026-08-21 | Q43: 2027-02-15 | R43: 12 | S43: Pilot build follow-up | T43: Direct | V43: =IF(S43="",1,0) | W43: =IF(J43="",1,0) | X43: =IF(F43="",1,0) | Y43: =IF(AND(AND(H43<>"Mass production",H43<>"Lost"),DATEVALUE(Q43)<DATE(2026,10,20)),1,0) | Z43: =IF(AND(AND(H43<>"Mass production",H43<>"Lost"),R43>30),1,0) | AA43: =IF(COUNTIFS($G$2:$G$247,G43,$F$2:$F$247,F43,$J$2:$J$247,J43,$K$2:$K$247,K43)>1,1,0) | AB43: =SUM(V43:AA43)
A44: OPP-26042 | B44: Stellar Mobility | C44: DACH | D44: Switzerland | E44: L. Hoffmann | F44: POS & payments | G44: GNSS | H44: Qualified | I44: 0.1 | J44: 15000 | K44: 8.32 | L44: 5 | M44: 124800 | N44: 624000 | O44: 62400 | P44: 2025-05-05 | Q44: 2027-01-27 | R44: 63 | S44: Forecast confirmation | T44: Website | V44: =IF(S44="",1,0) | W44: =IF(J44="",1,0) | X44: =IF(F44="",1,0) | Y44: =IF(AND(AND(H44<>"Mass production",H44<>"Lost"),DATEVALUE(Q44)<DATE(2026,10,20)),1,0) | Z44: =IF(AND(AND(H44<>"Mass production",H44<>"Lost"),R44>30),1,0) | AA44: =IF(COUNTIFS($G$2:$G$247,G44,$F$2:$F$247,F44,$J$2:$J$247,J44,$K$2:$K$247,K44)>1,1,0) | AB44: =SUM(V44:AA44)
A45: OPP-26043 | B45: Meridian Telematics | C45: UK & Ireland | D45: Ireland | E45: S. Clarke | F45: Telematics | G45: 5G eMBB | H45: Qualified | I45: 0.1 | J45: 20000 | K45: 132.31 | L45: 5 | M45: 2646200 | N45: 13231000 | O45: 1323100 | P45: 2025-09-21 | Q45: 2026-10-26 | R45: 12 | S45: Forecast confirmation | T45: Tradeshow | V45: =IF(S45="",1,0) | W45: =IF(J45="",1,0) | X45: =IF(F45="",1,0) | Y45: =IF(AND(AND(H45<>"Mass production",H45<>"Lost"),DATEVALUE(Q45)<DATE(2026,10,20)),1,0) | Z45: =IF(AND(AND(H45<>"Mass production",H45<>"Lost"),R45>30),1,0) | AA45: =IF(COUNTIFS($G$2:$G$247,G45,$F$2:$F$247,F45,$J$2:$J$247,J45,$K$2:$K$247,K45)>1,1,0) | AB45: =SUM(V45:AA45)
A46: OPP-26044 | B46: Vector Devices | C46: UK & Ireland | D46: United Kingdom | E46: S. Clarke | F46: Telematics | G46: Smart module | H46: Sample / Evaluation | I46: 0.2 | K46: 92.01 | L46: 3 | M46: 0 | N46: 0 | O46: 0 | P46: 2025-06-05 | Q46: 2026-09-22 | R46: 9 | S46: Pilot build follow-up | T46: Tradeshow | V46: =IF(S46="",1,0) | W46: =IF(J46="",1,0) | X46: =IF(F46="",1,0) | Y46: =IF(AND(AND(H46<>"Mass production",H46<>"Lost"),DATEVALUE(Q46)<DATE(2026,10,20)),1,0) | Z46: =IF(AND(AND(H46<>"Mass production",H46<>"Lost"),R46>30),1,0) | AA46: =IF(COUNTIFS($G$2:$G$247,G46,$F$2:$F$247,F46,$J$2:$J$247,J46,$K$2:$K$247,K46)>1,1,0) | AB46: =SUM(V46:AA46)
A47: OPP-26045 | B47: Solent Devices | C47: Nordics | D47: Norway | E47: E. Lindqvist | F47: Asset tracking | G47: LTE Cat 1 bis | H47: Lost | I47: 0 | J47: 3000 | K47: 10.99 | L47: 2 | M47: 32970 | N47: 65940 | O47: 0 | P47: 2026-02-02 | Q47: 2026-10-15 | R47: 29 | S47: Design review | T47: Tradeshow | U47: Certification timeline | V47: =IF(S47="",1,0) | W47: =IF(J47="",1,0) | X47: =IF(F47="",1,0) | Y47: =IF(AND(AND(H47<>"Mass production",H47<>"Lost"),DATEVALUE(Q47)<DATE(2026,10,20)),1,0) | Z47: =IF(AND(AND(H47<>"Mass production",H47<>"Lost"),R47>30),1,0) | AA47: =IF(COUNTIFS($G$2:$G$247,G47,$F$2:$F$247,F47,$J$2:$J$247,J47,$K$2:$K$247,K47)>1,1,0) | AB47: =SUM(V47:AA47)
A48: OPP-26046 | B48: Cedar Mobility | C48: Middle East & Africa | D48: UAE | E48: O. Demir | F48: Smart metering | G48: LTE Cat 1 bis | H48: Lead | I48: 0.05 | J48: 30000 | K48: 8.26 | L48: 3 | M48: 247800 | N48: 743400 | O48: 37170 | P48: 2025-09-24 | Q48: 2026-10-30 | R48: 100 | S48: Design review | T48: Direct | V48: =IF(S48="",1,0) | W48: =IF(J48="",1,0) | X48: =IF(F48="",1,0) | Y48: =IF(AND(AND(H48<>"Mass production",H48<>"Lost"),DATEVALUE(Q48)<DATE(2026,10,20)),1,0) | Z48: =IF(AND(AND(H48<>"Mass production",H48<>"Lost"),R48>30),1,0) | AA48: =IF(COUNTIFS($G$2:$G$247,G48,$F$2:$F$247,F48,$J$2:$J$247,J48,$K$2:$K$247,K48)>1,1,0) | AB48: =SUM(V48:AA48)
A49: OPP-26047 | B49: Pannon Systems | C49: France & Benelux | D49: Netherlands | E49: C. Martin | F49: Automotive & C-V2X | G49: 5G eMBB | H49: Lead | I49: 0.05 | J49: 80000 | K49: 120.29 | L49: 2 | M49: 9623200 | N49: 19246400 | O49: 962320 | P49: 2026-08-10 | Q49: 2027-10-17 | R49: 22 | S49: Certification plan | T49: Distributor | V49: =IF(S49="",1,0) | W49: =IF(J49="",1,0) | X49: =IF(F49="",1,0) | Y49: =IF(AND(AND(H49<>"Mass production",H49<>"Lost"),DATEVALUE(Q49)<DATE(2026,10,20)),1,0) | Z49: =IF(AND(AND(H49<>"Mass production",H49<>"Lost"),R49>30),1,0) | AA49: =IF(COUNTIFS($G$2:$G$247,G49,$F$2:$F$247,F49,$J$2:$J$247,J49,$K$2:$K$247,K49)>1,1,0) | AB49: =SUM(V49:AA49)
A50: OPP-26048 | B50: Meridian Systems | C50: Southern Europe | D50: Portugal | E50: M. Rossi | F50: Asset tracking | G50: 5G eMBB | H50: Sample / Evaluation | I50: 0.2 | J50: 80000 | K50: 128.38 | L50: 2 | M50: 10270400 | N50: 20540800 | O50: 4108160 | P50: 2025-12-21 | Q50: 2026-11-23 | R50: 2 | S50: Send samples | T50: Distributor | V50: =IF(S50="",1,0) | W50: =IF(J50="",1,0) | X50: =IF(F50="",1,0) | Y50: =IF(AND(AND(H50<>"Mass production",H50<>"Lost"),DATEVALUE(Q50)<DATE(2026,10,20)),1,0) | Z50: =IF(AND(AND(H50<>"Mass production",H50<>"Lost"),R50>30),1,0) | AA50: =IF(COUNTIFS($G$2:$G$247,G50,$F$2:$F$247,F50,$J$2:$J$247,J50,$K$2:$K$247,K50)>1,1,0) | AB50: =SUM(V50:AA50)
A51: OPP-26049 | B51: Zenit Tracking | C51: UK & Ireland | D51: Ireland | E51: R. Patel | F51: Automotive & C-V2X | G51: 5G eMBB | H51: Sample / Evaluation | I51: 0.2 | J51: 5000 | K51: 99.6 | L51: 4 | M51: 498000 | N51: 1992000 | O51: 398400 | P51: 2025-04-10 | Q51: 2026-11-07 | R51: 11 | S51: Price negotiation | T51: Distributor | V51: =IF(S51="",1,0) | W51: =IF(J51="",1,0) | X51: =IF(F51="",1,0) | Y51: =IF(AND(AND(H51<>"Mass production",H51<>"Lost"),DATEVALUE(Q51)<DATE(2026,10,20)),1,0) | Z51: =IF(AND(AND(H51<>"Mass production",H51<>"Lost"),R51>30),1,0) | AA51: =IF(COUNTIFS($G$2:$G$247,G51,$F$2:$F$247,F51,$J$2:$J$247,J51,$K$2:$K$247,K51)>1,1,0) | AB51: =SUM(V51:AA51)
A52: OPP-26050 | B52: Solent Devices | C52: Nordics | D52: Norway | E52: E. Lindqvist | F52: Telematics | G52: Wi-Fi / Bluetooth | H52: Pilot | I52: 0.85 | J52: 10000 | K52: 4.81 | L52: 4 | M52: 48100 | N52: 192400 | O52: 163540 | P52: 2026-08-30 | Q52: 2026-10-11 | R52: 27 | S52: Technical review call | T52: FAE referral | V52: =IF(S52="",1,0) | W52: =IF(J52="",1,0) | X52: =IF(F52="",1,0) | Y52: =IF(AND(AND(H52<>"Mass production",H52<>"Lost"),DATEVALUE(Q52)<DATE(2026,10,20)),1,0) | Z52: =IF(AND(AND(H52<>"Mass production",H52<>"Lost"),R52>30),1,0) | AA52: =IF(COUNTIFS($G$2:$G$247,G52,$F$2:$F$247,F52,$J$2:$J$247,J52,$K$2:$K$247,K52)>1,1,0) | AB52: =SUM(V52:AA52)
A53: OPP-26051 | B53: Atlas Tracking | C53: DACH | D53: Switzerland | E53: L. Hoffmann | F53: Automotive & C-V2X | G53: LTE Cat 1 bis | H53: Lead | I53: 0.05 | J53: 80000 | K53: 9.69 | L53: 5 | M53: 775200 | N53: 3876000 | O53: 193800 | P53: 2025-11-02 | Q53: 2027-03-24 | R53: 9 | S53: Technical review call | T53: Website | V53: =IF(S53="",1,0) | W53: =IF(J53="",1,0) | X53: =IF(F53="",1,0) | Y53: =IF(AND(AND(H53<>"Mass production",H53<>"Lost"),DATEVALUE(Q53)<DATE(2026,10,20)),1,0) | Z53: =IF(AND(AND(H53<>"Mass production",H53<>"Lost"),R53>30),1,0) | AA53: =IF(COUNTIFS($G$2:$G$247,G53,$F$2:$F$247,F53,$J$2:$J$247,J53,$K$2:$K$247,K53)>1,1,0) | AB53: =SUM(V53:AA53)
A54: OPP-26052 | B54: Arcturus Labs | C54: DACH | D54: Switzerland | E54: L. Hoffmann | F54: POS & payments | G54: 5G eMBB | H54: Pilot | I54: 0.85 | J54: 8000 | K54: 108.65 | L54: 4 | M54: 869200 | N54: 3476800 | O54: 2955280 | P54: 2025-10-18 | Q54: 2027-04-30 | R54: 6 | S54: Forecast confirmation | T54: FAE referral | V54: =IF(S54="",1,0) | W54: =IF(J54="",1,0) | X54: =IF(F54="",1,0) | Y54: =IF(AND(AND(H54<>"Mass production",H54<>"Lost"),DATEVALUE(Q54)<DATE(2026,10,20)),1,0) | Z54: =IF(AND(AND(H54<>"Mass production",H54<>"Lost"),R54>30),1,0) | AA54: =IF(COUNTIFS($G$2:$G$247,G54,$F$2:$F$247,F54,$J$2:$J$247,J54,$K$2:$K$247,K54)>1,1,0) | AB54: =SUM(V54:AA54)
A55: OPP-26053 | B55: Meridian Metering | C55: Southern Europe | D55: Portugal | E55: A. Garcia | F55: Automotive & C-V2X | G55: Wi-Fi / Bluetooth | H55: Lead | I55: 0.05 | J55: 20000 | K55: 2.8 | L55: 2 | M55: 56000 | N55: 112000 | O55: 5600 | P55: 2025-09-14 | Q55: 2027-10-30 | R55: 106 | S55: Design review | T55: Distributor | V55: =IF(S55="",1,0) | W55: =IF(J55="",1,0) | X55: =IF(F55="",1,0) | Y55: =IF(AND(AND(H55<>"Mass production",H55<>"Lost"),DATEVALUE(Q55)<DATE(2026,10,20)),1,0) | Z55: =IF(AND(AND(H55<>"Mass production",H55<>"Lost"),R55>30),1,0) | AA55: =IF(COUNTIFS($G$2:$G$247,G55,$F$2:$F$247,F55,$J$2:$J$247,J55,$K$2:$K$247,K55)>1,1,0) | AB55: =SUM(V55:AA55)
A56: OPP-26054 | B56: Sava Labs | C56: DACH | D56: Germany | E56: J. Weber | F56: Automotive & C-V2X | G56: Smart module | H56: Mass production | I56: 1 | J56: 10000 | K56: 47.57 | L56: 5 | M56: 475700 | N56: 2378500 | O56: 2378500 | P56: 2025-11-15 | Q56: 2026-09-11 | R56: 21 | S56: Forecast confirmation | T56: Website | V56: =IF(S56="",1,0) | W56: =IF(J56="",1,0) | X56: =IF(F56="",1,0) | Y56: =IF(AND(AND(H56<>"Mass production",H56<>"Lost"),DATEVALUE(Q56)<DATE(2026,10,20)),1,0) | Z56: =IF(AND(AND(H56<>"Mass production",H56<>"Lost"),R56>30),1,0) | AA56: =IF(COUNTIFS($G$2:$G$247,G56,$F$2:$F$247,F56,$J$2:$J$247,J56,$K$2:$K$247,K56)>1,1,0) | AB56: =SUM(V56:AA56)
A57: OPP-26055 | B57: Cedar Mobility | C57: Middle East & Africa | D57: UAE | E57: O. Demir | F57: Healthcare | G57: Wi-Fi / Bluetooth | H57: Design-in | I57: 0.4 | J57: 50000 | K57: 4 | L57: 5 | M57: 200000 | N57: 1000000 | O57: 400000 | P57: 2025-03-09 | Q57: 2026-09-23 | R57: 9 | S57: Forecast confirmation | T57: Direct | V57: =IF(S57="",1,0) | W57: =IF(J57="",1,0) | X57: =IF(F57="",1,0) | Y57: =IF(AND(AND(H57<>"Mass production",H57<>"Lost"),DATEVALUE(Q57)<DATE(2026,10,20)),1,0) | Z57: =IF(AND(AND(H57<>"Mass production",H57<>"Lost"),R57>30),1,0) | AA57: =IF(COUNTIFS($G$2:$G$247,G57,$F$2:$F$247,F57,$J$2:$J$247,J57,$K$2:$K$247,K57)>1,1,0) | AB57: =SUM(V57:AA57)
A58: OPP-26056 | B58: Bluecell Labs | C58: Southern Europe | D58: Portugal | E58: A. Garcia | F58: POS & payments | G58: 5G RedCap | H58: Design-win | I58: 0.7 | J58: 2000 | K58: 41.4 | L58: 2 | M58: 82800 | N58: 165600 | O58: 115920 | P58: 2025-04-05 | Q58: 2026-12-29 | R58: 6 | S58: Forecast confirmation | T58: Tradeshow | V58: =IF(S58="",1,0) | W58: =IF(J58="",1,0) | X58: =IF(F58="",1,0) | Y58: =IF(AND(AND(H58<>"Mass production",H58<>"Lost"),DATEVALUE(Q58)<DATE(2026,10,20)),1,0) | Z58: =IF(AND(AND(H58<>"Mass production",H58<>"Lost"),R58>30),1,0) | AA58: =IF(COUNTIFS($G$2:$G$247,G58,$F$2:$F$247,F58,$J$2:$J$247,J58,$K$2:$K$247,K58)>1,1,0) | AB58: =SUM(V58:AA58)
A59: OPP-26057 | B59: Orbis Connect | C59: UK & Ireland | D59: United Kingdom | E59: R. Patel | F59: POS & payments | G59: 5G eMBB | H59: Lost | I59: 0 | J59: 80000 | K59: 93.66 | L59: 2 | M59: 7492800 | N59: 14985600 | O59: 0 | P59: 2026-07-09 | Q59: 2026-10-05 | R59: 28 | S59: Certification plan | T59: Tradeshow | U59: Price | V59: =IF(S59="",1,0) | W59: =IF(J59="",1,0) | X59: =IF(F59="",1,0) | Y59: =IF(AND(AND(H59<>"Mass production",H59<>"Lost"),DATEVALUE(Q59)<DATE(2026,10,20)),1,0) | Z59: =IF(AND(AND(H59<>"Mass production",H59<>"Lost"),R59>30),1,0) | AA59: =IF(COUNTIFS($G$2:$G$247,G59,$F$2:$F$247,F59,$J$2:$J$247,J59,$K$2:$K$247,K59)>1,1,0) | AB59: =SUM(V59:AA59)
A60: OPP-26058 | B60: Zenit Devices | C60: Nordics | D60: Sweden | E60: E. Lindqvist | F60: Asset tracking | G60: Smart module | H60: Sample / Evaluation | I60: 0.2 | K60: 74.66 | L60: 3 | M60: 0 | N60: 0 | O60: 0 | P60: 2026-08-15 | Q60: 2026-12-31 | R60: 6 | S60: Pilot build follow-up | T60: Direct | V60: =IF(S60="",1,0) | W60: =IF(J60="",1,0) | X60: =IF(F60="",1,0) | Y60: =IF(AND(AND(H60<>"Mass production",H60<>"Lost"),DATEVALUE(Q60)<DATE(2026,10,20)),1,0) | Z60: =IF(AND(AND(H60<>"Mass production",H60<>"Lost"),R60>30),1,0) | AA60: =IF(COUNTIFS($G$2:$G$247,G60,$F$2:$F$247,F60,$J$2:$J$247,J60,$K$2:$K$247,K60)>1,1,0) | AB60: =SUM(V60:AA60)
A61: OPP-26059 | B61: Ferro Labs | C61: DACH | D61: Austria | E61: L. Hoffmann | F61: Automotive & C-V2X | G61: 5G eMBB | H61: Pilot | I61: 0.85 | J61: 50000 | K61: 92.11 | L61: 3 | M61: 4605500 | N61: 13816500 | O61: 11744025 | P61: 2025-05-06 | Q61: 2027-03-10 | R61: 1 | S61: Forecast confirmation | T61: Distributor | V61: =IF(S61="",1,0) | W61: =IF(J61="",1,0) | X61: =IF(F61="",1,0) | Y61: =IF(AND(AND(H61<>"Mass production",H61<>"Lost"),DATEVALUE(Q61)<DATE(2026,10,20)),1,0) | Z61: =IF(AND(AND(H61<>"Mass production",H61<>"Lost"),R61>30),1,0) | AA61: =IF(COUNTIFS($G$2:$G$247,G61,$F$2:$F$247,F61,$J$2:$J$247,J61,$K$2:$K$247,K61)>1,1,0) | AB61: =SUM(V61:AA61)
A62: OPP-26060 | B62: Stellar Labs | C62: DACH | D62: Austria | E62: J. Weber | F62: Industrial IoT | G62: LTE Cat 1 bis | H62: Design-win | I62: 0.7 | J62: 2000 | K62: 7.9 | L62: 3 | M62: 15800 | N62: 47400 | O62: 33180 | P62: 2026-04-08 | Q62: 2027-05-03 | R62: 13 | S62: Design review | T62: Distributor | V62: =IF(S62="",1,0) | W62: =IF(J62="",1,0) | X62: =IF(F62="",1,0) | Y62: =IF(AND(AND(H62<>"Mass production",H62<>"Lost"),DATEVALUE(Q62)<DATE(2026,10,20)),1,0) | Z62: =IF(AND(AND(H62<>"Mass production",H62<>"Lost"),R62>30),1,0) | AA62: =IF(COUNTIFS($G$2:$G$247,G62,$F$2:$F$247,F62,$J$2:$J$247,J62,$K$2:$K$247,K62)>1,1,0) | AB62: =SUM(V62:AA62)
A63: OPP-26061 | B63: Nordwind Telematics | C63: Nordics | D63: Sweden | E63: E. Lindqvist | F63: Industrial IoT | G63: Smart module | H63: Mass production | I63: 1 | J63: 15000 | K63: 61.98 | L63: 3 | M63: 929700 | N63: 2789100 | O63: 2789100 | P63: 2026-07-14 | Q63: 2026-09-29 | R63: 1 | S63: Technical review call | T63: Direct | V63: =IF(S63="",1,0) | W63: =IF(J63="",1,0) | X63: =IF(F63="",1,0) | Y63: =IF(AND(AND(H63<>"Mass production",H63<>"Lost"),DATEVALUE(Q63)<DATE(2026,10,20)),1,0) | Z63: =IF(AND(AND(H63<>"Mass production",H63<>"Lost"),R63>30),1,0) | AA63: =IF(COUNTIFS($G$2:$G$247,G63,$F$2:$F$247,F63,$J$2:$J$247,J63,$K$2:$K$247,K63)>1,1,0) | AB63: =SUM(V63:AA63)
A64: OPP-26062 | B64: Baltix Telematics | C64: DACH | D64: Germany | E64: L. Hoffmann | F64: Healthcare | G64: Wi-Fi / Bluetooth | H64: Qualified | I64: 0.1 | J64: 5000 | K64: 4.79 | L64: 4 | M64: 23950 | N64: 95800 | O64: 9580 | P64: 2025-06-12 | Q64: 2027-10-01 | R64: 118 | S64: Quote revision | T64: Distributor | V64: =IF(S64="",1,0) | W64: =IF(J64="",1,0) | X64: =IF(F64="",1,0) | Y64: =IF(AND(AND(H64<>"Mass production",H64<>"Lost"),DATEVALUE(Q64)<DATE(2026,10,20)),1,0) | Z64: =IF(AND(AND(H64<>"Mass production",H64<>"Lost"),R64>30),1,0) | AA64: =IF(COUNTIFS($G$2:$G$247,G64,$F$2:$F$247,F64,$J$2:$J$247,J64,$K$2:$K$247,K64)>1,1,0) | AB64: =SUM(V64:AA64)
A65: OPP-26063 | B65: Iberix Metering | C65: Southern Europe | D65: Portugal | E65: A. Garcia | F65: Automotive & C-V2X | G65: LTE Cat 1 bis | H65: Sample / Evaluation | I65: 0.2 | J65: 15000 | K65: 9.57 | L65: 5 | M65: 143550 | N65: 717750 | O65: 143550 | P65: 2026-07-17 | Q65: 2027-02-15 | R65: 7 | S65: Technical review call | T65: Tradeshow | V65: =IF(S65="",1,0) | W65: =IF(J65="",1,0) | X65: =IF(F65="",1,0) | Y65: =IF(AND(AND(H65<>"Mass production",H65<>"Lost"),DATEVALUE(Q65)<DATE(2026,10,20)),1,0) | Z65: =IF(AND(AND(H65<>"Mass production",H65<>"Lost"),R65>30),1,0) | AA65: =IF(COUNTIFS($G$2:$G$247,G65,$F$2:$F$247,F65,$J$2:$J$247,J65,$K$2:$K$247,K65)>1,1,0) | AB65: =SUM(V65:AA65)
A66: OPP-26064 | B66: Pannon Devices | C66: CEE | D66: Poland | E66: K. Nowak | F66: Telematics | G66: Wi-Fi / Bluetooth | H66: Design-win | I66: 0.7 | J66: 2000 | K66: 5.09 | L66: 4 | M66: 10180 | N66: 40720 | O66: 28504 | P66: 2025-02-22 | Q66: 2026-12-15 | R66: 5 | S66: Technical review call | T66: Website | V66: =IF(S66="",1,0) | W66: =IF(J66="",1,0) | X66: =IF(F66="",1,0) | Y66: =IF(AND(AND(H66<>"Mass production",H66<>"Lost"),DATEVALUE(Q66)<DATE(2026,10,20)),1,0) | Z66: =IF(AND(AND(H66<>"Mass production",H66<>"Lost"),R66>30),1,0) | AA66: =IF(COUNTIFS($G$2:$G$247,G66,$F$2:$F$247,F66,$J$2:$J$247,J66,$K$2:$K$247,K66)>1,1,0) | AB66: =SUM(V66:AA66)
A67: OPP-26065 | B67: Orbis Metering | C67: CEE | D67: Czechia | E67: D. Jovanovic | F67: Smart home & security | G67: Smart module | H67: Lead | I67: 0.05 | J67: 8000 | K67: 53.63 | L67: 4 | M67: 429040 | N67: 1716160 | O67: 85808 | P67: 2025-07-08 | Q67: 2027-06-05 | R67: 8 | S67: Design review | T67: Tradeshow | V67: =IF(S67="",1,0) | W67: =IF(J67="",1,0) | X67: =IF(F67="",1,0) | Y67: =IF(AND(AND(H67<>"Mass production",H67<>"Lost"),DATEVALUE(Q67)<DATE(2026,10,20)),1,0) | Z67: =IF(AND(AND(H67<>"Mass production",H67<>"Lost"),R67>30),1,0) | AA67: =IF(COUNTIFS($G$2:$G$247,G67,$F$2:$F$247,F67,$J$2:$J$247,J67,$K$2:$K$247,K67)>1,1,0) | AB67: =SUM(V67:AA67)
A68: OPP-26066 | B68: Arcturus Industrial | C68: Southern Europe | D68: Italy | E68: M. Rossi | F68: Healthcare | G68: Smart module | H68: Mass production | I68: 1 | J68: 15000 | K68: 61.73 | L68: 2 | M68: 925950 | N68: 1851900 | O68: 1851900 | P68: 2025-03-08 | Q68: 2026-01-19 | R68: 4 | S68: Pilot build follow-up | T68: FAE referral | V68: =IF(S68="",1,0) | W68: =IF(J68="",1,0) | X68: =IF(F68="",1,0) | Y68: =IF(AND(AND(H68<>"Mass production",H68<>"Lost"),DATEVALUE(Q68)<DATE(2026,10,20)),1,0) | Z68: =IF(AND(AND(H68<>"Mass production",H68<>"Lost"),R68>30),1,0) | AA68: =IF(COUNTIFS($G$2:$G$247,G68,$F$2:$F$247,F68,$J$2:$J$247,J68,$K$2:$K$247,K68)>1,1,0) | AB68: =SUM(V68:AA68)
A69: OPP-26067 | B69: Nordwind Telematics | C69: Nordics | D69: Sweden | E69: E. Lindqvist | F69: Smart home & security | G69: Smart module | H69: Qualified | I69: 0.1 | J69: 10000 | K69: 91.9 | L69: 5 | M69: 919000 | N69: 4595000 | O69: 459500 | P69: 2025-09-10 | Q69: 2027-08-05 | R69: 25 | S69: Forecast confirmation | T69: Direct | V69: =IF(S69="",1,0) | W69: =IF(J69="",1,0) | X69: =IF(F69="",1,0) | Y69: =IF(AND(AND(H69<>"Mass production",H69<>"Lost"),DATEVALUE(Q69)<DATE(2026,10,20)),1,0) | Z69: =IF(AND(AND(H69<>"Mass production",H69<>"Lost"),R69>30),1,0) | AA69: =IF(COUNTIFS($G$2:$G$247,G69,$F$2:$F$247,F69,$J$2:$J$247,J69,$K$2:$K$247,K69)>1,1,0) | AB69: =SUM(V69:AA69)
A70: OPP-26068 | B70: Orbis Devices | C70: Middle East & Africa | D70: UAE | E70: Y. Cohen | F70: Healthcare | G70: Wi-Fi / Bluetooth | H70: Sample / Evaluation | I70: 0.2 | J70: 8000 | K70: 4.2 | L70: 3 | M70: 33600 | N70: 100800 | O70: 20160 | P70: 2026-04-25 | Q70: 2026-09-17 | R70: 18 | S70: Quote revision | T70: Distributor | V70: =IF(S70="",1,0) | W70: =IF(J70="",1,0) | X70: =IF(F70="",1,0) | Y70: =IF(AND(AND(H70<>"Mass production",H70<>"Lost"),DATEVALUE(Q70)<DATE(2026,10,20)),1,0) | Z70: =IF(AND(AND(H70<>"Mass production",H70<>"Lost"),R70>30),1,0) | AA70: =IF(COUNTIFS($G$2:$G$247,G70,$F$2:$F$247,F70,$J$2:$J$247,J70,$K$2:$K$247,K70)>1,1,0) | AB70: =SUM(V70:AA70)
A71: OPP-26069 | B71: Corvid Health | C71: DACH | D71: Germany | E71: L. Hoffmann | F71: Industrial IoT | G71: Wi-Fi / Bluetooth | H71: Mass production | I71: 1 | J71: 30000 | K71: 5.66 | L71: 2 | M71: 169800 | N71: 339600 | O71: 339600 | P71: 2025-08-06 | Q71: 2026-06-08 | R71: 22 | S71: Certification plan | T71: Direct | V71: =IF(S71="",1,0) | W71: =IF(J71="",1,0) | X71: =IF(F71="",1,0) | Y71: =IF(AND(AND(H71<>"Mass production",H71<>"Lost"),DATEVALUE(Q71)<DATE(2026,10,20)),1,0) | Z71: =IF(AND(AND(H71<>"Mass production",H71<>"Lost"),R71>30),1,0) | AA71: =IF(COUNTIFS($G$2:$G$247,G71,$F$2:$F$247,F71,$J$2:$J$247,J71,$K$2:$K$247,K71)>1,1,0) | AB71: =SUM(V71:AA71)
A72: OPP-26070 | B72: Meridian Metering | C72: Southern Europe | D72: Portugal | E72: M. Rossi | F72: POS & payments | G72: 5G eMBB | H72: Lost | I72: 0 | J72: 80000 | K72: 105.23 | L72: 4 | M72: 8418400 | N72: 33673600 | O72: 0 | P72: 2025-06-15 | Q72: 2026-03-06 | R72: 28 | S72: Send samples | T72: Tradeshow | U72: Project cancelled | V72: =IF(S72="",1,0) | W72: =IF(J72="",1,0) | X72: =IF(F72="",1,0) | Y72: =IF(AND(AND(H72<>"Mass production",H72<>"Lost"),DATEVALUE(Q72)<DATE(2026,10,20)),1,0) | Z72: =IF(AND(AND(H72<>"Mass production",H72<>"Lost"),R72>30),1,0) | AA72: =IF(COUNTIFS($G$2:$G$247,G72,$F$2:$F$247,F72,$J$2:$J$247,J72,$K$2:$K$247,K72)>1,1,0) | AB72: =SUM(V72:AA72)
A73: OPP-26071 | B73: Baltix Devices | C73: Nordics | D73: Sweden | E73: E. Lindqvist | F73: Telematics | G73: GNSS | H73: Pilot | I73: 0.85 | J73: 10000 | K73: 8.18 | L73: 2 | M73: 81800 | N73: 163600 | O73: 139060 | P73: 2026-04-19 | Q73: 2027-01-27 | R73: 7 | S73: Forecast confirmation | T73: FAE referral | V73: =IF(S73="",1,0) | W73: =IF(J73="",1,0) | X73: =IF(F73="",1,0) | Y73: =IF(AND(AND(H73<>"Mass production",H73<>"Lost"),DATEVALUE(Q73)<DATE(2026,10,20)),1,0) | Z73: =IF(AND(AND(H73<>"Mass production",H73<>"Lost"),R73>30),1,0) | AA73: =IF(COUNTIFS($G$2:$G$247,G73,$F$2:$F$247,F73,$J$2:$J$247,J73,$K$2:$K$247,K73)>1,1,0) | AB73: =SUM(V73:AA73)
A74: OPP-26072 | B74: Nordwind Telematics | C74: Nordics | D74: Sweden | E74: E. Lindqvist | F74: Asset tracking | G74: 5G eMBB | H74: Design-in | I74: 0.4 | J74: 3000 | K74: 106.24 | L74: 3 | M74: 318720 | N74: 956160 | O74: 382464 | P74: 2026-02-13 | Q74: 2026-09-24 | R74: 5 | S74: Send samples | T74: Direct | V74: =IF(S74="",1,0) | W74: =IF(J74="",1,0) | X74: =IF(F74="",1,0) | Y74: =IF(AND(AND(H74<>"Mass production",H74<>"Lost"),DATEVALUE(Q74)<DATE(2026,10,20)),1,0) | Z74: =IF(AND(AND(H74<>"Mass production",H74<>"Lost"),R74>30),1,0) | AA74: =IF(COUNTIFS($G$2:$G$247,G74,$F$2:$F$247,F74,$J$2:$J$247,J74,$K$2:$K$247,K74)>1,1,0) | AB74: =SUM(V74:AA74)
A75: OPP-26073 | B75: Morava Systems | C75: France & Benelux | D75: Netherlands | E75: B. de Vries | G75: Wi-Fi / Bluetooth | H75: Mass production | I75: 1 | J75: 30000 | K75: 4.97 | L75: 5 | M75: 149100 | N75: 745500 | O75: 745500 | P75: 2026-09-25 | Q75: 2026-10-19 | R75: 4 | S75: Pilot build follow-up | T75: Direct | V75: =IF(S75="",1,0) | W75: =IF(J75="",1,0) | X75: =IF(F75="",1,0) | Y75: =IF(AND(AND(H75<>"Mass production",H75<>"Lost"),DATEVALUE(Q75)<DATE(2026,10,20)),1,0) | Z75: =IF(AND(AND(H75<>"Mass production",H75<>"Lost"),R75>30),1,0) | AA75: =IF(COUNTIFS($G$2:$G$247,G75,$F$2:$F$247,F75,$J$2:$J$247,J75,$K$2:$K$247,K75)>1,1,0) | AB75: =SUM(V75:AA75)
A76: OPP-26074 | B76: Corvid Connect | C76: DACH | D76: Austria | E76: J. Weber | F76: Asset tracking | G76: Wi-Fi / Bluetooth | H76: Sample / Evaluation | I76: 0.2 | J76: 3000 | K76: 4.68 | L76: 2 | M76: 14040 | N76: 28080 | O76: 5616 | P76: 2025-05-07 | Q76: 2027-07-12 | R76: 8 | S76: Pilot build follow-up | T76: Distributor | V76: =IF(S76="",1,0) | W76: =IF(J76="",1,0) | X76: =IF(F76="",1,0) | Y76: =IF(AND(AND(H76<>"Mass production",H76<>"Lost"),DATEVALUE(Q76)<DATE(2026,10,20)),1,0) | Z76: =IF(AND(AND(H76<>"Mass production",H76<>"Lost"),R76>30),1,0) | AA76: =IF(COUNTIFS($G$2:$G$247,G76,$F$2:$F$247,F76,$J$2:$J$247,J76,$K$2:$K$247,K76)>1,1,0) | AB76: =SUM(V76:AA76)
A77: OPP-26075 | B77: Corvid Connect | C77: DACH | D77: Austria | E77: J. Weber | F77: Smart home & security | G77: 5G eMBB | H77: Design-in | I77: 0.4 | J77: 3000 | K77: 121.54 | L77: 5 | M77: 364620 | N77: 1823100 | O77: 729240 | P77: 2025-09-26 | Q77: 2026-10-14 | R77: 80 | T77: Direct | V77: =IF(S77="",1,0) | W77: =IF(J77="",1,0) | X77: =IF(F77="",1,0) | Y77: =IF(AND(AND(H77<>"Mass production",H77<>"Lost"),DATEVALUE(Q77)<DATE(2026,10,20)),1,0) | Z77: =IF(AND(AND(H77<>"Mass production",H77<>"Lost"),R77>30),1,0) | AA77: =IF(COUNTIFS($G$2:$G$247,G77,$F$2:$F$247,F77,$J$2:$J$247,J77,$K$2:$K$247,K77)>1,1,0) | AB77: =SUM(V77:AA77)
A78: OPP-26076 | B78: Kestrel Systems | C78: DACH | D78: Austria | E78: J. Weber | F78: Telematics | G78: Smart module | H78: Sample / Evaluation | I78: 0.2 | J78: 3000 | K78: 77.86 | L78: 5 | M78: 233580 | N78: 1167900 | O78: 233580 | P78: 2025-10-25 | Q78: 2026-11-17 | R78: 0 | S78: Price negotiation | T78: Tradeshow | V78: =IF(S78="",1,0) | W78: =IF(J78="",1,0) | X78: =IF(F78="",1,0) | Y78: =IF(AND(AND(H78<>"Mass production",H78<>"Lost"),DATEVALUE(Q78)<DATE(2026,10,20)),1,0) | Z78: =IF(AND(AND(H78<>"Mass production",H78<>"Lost"),R78>30),1,0) | AA78: =IF(COUNTIFS($G$2:$G$247,G78,$F$2:$F$247,F78,$J$2:$J$247,J78,$K$2:$K$247,K78)>1,1,0) | AB78: =SUM(V78:AA78)
A79: OPP-26077 | B79: Kestrel Systems | C79: DACH | D79: Austria | E79: L. Hoffmann | F79: POS & payments | G79: LTE-M / NB-IoT | H79: Pilot | I79: 0.85 | J79: 8000 | K79: 5.61 | L79: 2 | M79: 44880 | N79: 89760 | O79: 76296 | P79: 2026-03-10 | Q79: 2026-10-01 | R79: 5 | S79: Send samples | T79: Tradeshow | V79: =IF(S79="",1,0) | W79: =IF(J79="",1,0) | X79: =IF(F79="",1,0) | Y79: =IF(AND(AND(H79<>"Mass production",H79<>"Lost"),DATEVALUE(Q79)<DATE(2026,10,20)),1,0) | Z79: =IF(AND(AND(H79<>"Mass production",H79<>"Lost"),R79>30),1,0) | AA79: =IF(COUNTIFS($G$2:$G$247,G79,$F$2:$F$247,F79,$J$2:$J$247,J79,$K$2:$K$247,K79)>1,1,0) | AB79: =SUM(V79:AA79)
A80: OPP-26078 | B80: Kestrel Health | C80: CEE | D80: Hungary | E80: D. Jovanovic | F80: Healthcare | G80: 5G RedCap | H80: Mass production | I80: 1 | J80: 15000 | K80: 58.78 | L80: 3 | M80: 881700 | N80: 2645100 | O80: 2645100 | P80: 2026-05-26 | Q80: 2026-10-06 | R80: 87 | S80: Quote revision | T80: Distributor | V80: =IF(S80="",1,0) | W80: =IF(J80="",1,0) | X80: =IF(F80="",1,0) | Y80: =IF(AND(AND(H80<>"Mass production",H80<>"Lost"),DATEVALUE(Q80)<DATE(2026,10,20)),1,0) | Z80: =IF(AND(AND(H80<>"Mass production",H80<>"Lost"),R80>30),1,0) | AA80: =IF(COUNTIFS($G$2:$G$247,G80,$F$2:$F$247,F80,$J$2:$J$247,J80,$K$2:$K$247,K80)>1,1,0) | AB80: =SUM(V80:AA80)
A81: OPP-26079 | B81: Baltix Energy | C81: France & Benelux | D81: Belgium | E81: B. de Vries | F81: POS & payments | G81: 5G RedCap | H81: Sample / Evaluation | I81: 0.2 | J81: 3000 | K81: 55.45 | L81: 4 | M81: 166350 | N81: 665400 | O81: 133080 | P81: 2025-01-22 | Q81: 2026-12-11 | R81: 8 | S81: Pilot build follow-up | T81: Distributor | V81: =IF(S81="",1,0) | W81: =IF(J81="",1,0) | X81: =IF(F81="",1,0) | Y81: =IF(AND(AND(H81<>"Mass production",H81<>"Lost"),DATEVALUE(Q81)<DATE(2026,10,20)),1,0) | Z81: =IF(AND(AND(H81<>"Mass production",H81<>"Lost"),R81>30),1,0) | AA81: =IF(COUNTIFS($G$2:$G$247,G81,$F$2:$F$247,F81,$J$2:$J$247,J81,$K$2:$K$247,K81)>1,1,0) | AB81: =SUM(V81:AA81)
A82: OPP-26080 | B82: Vector Metering | C82: DACH | D82: Germany | E82: L. Hoffmann | F82: Healthcare | G82: LTE Cat 1 bis | H82: Design-win | I82: 0.7 | J82: 15000 | K82: 9.06 | L82: 5 | M82: 135900 | N82: 679500 | O82: 475650 | P82: 2025-07-12 | Q82: 2026-07-25 | R82: 16 | S82: Quote revision | T82: FAE referral | V82: =IF(S82="",1,0) | W82: =IF(J82="",1,0) | X82: =IF(F82="",1,0) | Y82: =IF(AND(AND(H82<>"Mass production",H82<>"Lost"),DATEVALUE(Q82)<DATE(2026,10,20)),1,0) | Z82: =IF(AND(AND(H82<>"Mass production",H82<>"Lost"),R82>30),1,0) | AA82: =IF(COUNTIFS($G$2:$G$247,G82,$F$2:$F$247,F82,$J$2:$J$247,J82,$K$2:$K$247,K82)>1,1,0) | AB82: =SUM(V82:AA82)
A83: OPP-26081 | B83: Alpenlink Metering | C83: UK & Ireland | D83: United Kingdom | E83: R. Patel | F83: Healthcare | G83: 5G RedCap | H83: Mass production | I83: 1 | J83: 8000 | K83: 41.03 | L83: 3 | M83: 328240 | N83: 984720 | O83: 984720 | P83: 2025-09-25 | Q83: 2026-08-07 | R83: 0 | S83: Price negotiation | T83: Tradeshow | V83: =IF(S83="",1,0) | W83: =IF(J83="",1,0) | X83: =IF(F83="",1,0) | Y83: =IF(AND(AND(H83<>"Mass production",H83<>"Lost"),DATEVALUE(Q83)<DATE(2026,10,20)),1,0) | Z83: =IF(AND(AND(H83<>"Mass production",H83<>"Lost"),R83>30),1,0) | AA83: =IF(COUNTIFS($G$2:$G$247,G83,$F$2:$F$247,F83,$J$2:$J$247,J83,$K$2:$K$247,K83)>1,1,0) | AB83: =SUM(V83:AA83)
A84: OPP-26082 | B84: Alpenlink Connect | C84: France & Benelux | D84: Belgium | E84: C. Martin | F84: POS & payments | G84: LTE Cat 1 bis | H84: Sample / Evaluation | I84: 0.2 | J84: 8000 | K84: 9.77 | L84: 2 | M84: 78160 | N84: 156320 | O84: 31264 | P84: 2026-09-04 | Q84: 2027-09-21 | R84: 2 | S84: Pilot build follow-up | T84: Tradeshow | V84: =IF(S84="",1,0) | W84: =IF(J84="",1,0) | X84: =IF(F84="",1,0) | Y84: =IF(AND(AND(H84<>"Mass production",H84<>"Lost"),DATEVALUE(Q84)<DATE(2026,10,20)),1,0) | Z84: =IF(AND(AND(H84<>"Mass production",H84<>"Lost"),R84>30),1,0) | AA84: =IF(COUNTIFS($G$2:$G$247,G84,$F$2:$F$247,F84,$J$2:$J$247,J84,$K$2:$K$247,K84)>1,1,0) | AB84: =SUM(V84:AA84)
A85: OPP-26083 | B85: Iberix Mobility | C85: DACH | D85: Austria | E85: L. Hoffmann | F85: Healthcare | G85: LTE-M / NB-IoT | H85: Sample / Evaluation | I85: 0.2 | J85: 5000 | K85: 6.1 | L85: 2 | M85: 30500 | N85: 61000 | O85: 12200 | P85: 2025-06-25 | Q85: 2026-12-07 | R85: 29 | S85: Technical review call | T85: Distributor | V85: =IF(S85="",1,0) | W85: =IF(J85="",1,0) | X85: =IF(F85="",1,0) | Y85: =IF(AND(AND(H85<>"Mass production",H85<>"Lost"),DATEVALUE(Q85)<DATE(2026,10,20)),1,0) | Z85: =IF(AND(AND(H85<>"Mass production",H85<>"Lost"),R85>30),1,0) | AA85: =IF(COUNTIFS($G$2:$G$247,G85,$F$2:$F$247,F85,$J$2:$J$247,J85,$K$2:$K$247,K85)>1,1,0) | AB85: =SUM(V85:AA85)
A86: OPP-26084 | B86: Orbis Systems | C86: France & Benelux | D86: Belgium | E86: C. Martin | F86: Healthcare | G86: Smart module | H86: Mass production | I86: 1 | J86: 5000 | K86: 80.48 | L86: 3 | M86: 402400 | N86: 1207200 | O86: 1207200 | P86: 2025-04-28 | Q86: 2025-12-18 | R86: 19 | S86: Forecast confirmation | T86: Distributor | V86: =IF(S86="",1,0) | W86: =IF(J86="",1,0) | X86: =IF(F86="",1,0) | Y86: =IF(AND(AND(H86<>"Mass production",H86<>"Lost"),DATEVALUE(Q86)<DATE(2026,10,20)),1,0) | Z86: =IF(AND(AND(H86<>"Mass production",H86<>"Lost"),R86>30),1,0) | AA86: =IF(COUNTIFS($G$2:$G$247,G86,$F$2:$F$247,F86,$J$2:$J$247,J86,$K$2:$K$247,K86)>1,1,0) | AB86: =SUM(V86:AA86)
A87: OPP-26085 | B87: Quorra Electronics | C87: DACH | D87: Austria | E87: L. Hoffmann | F87: Automotive & C-V2X | G87: 5G RedCap | H87: Design-win | I87: 0.7 | J87: 20000 | K87: 39.58 | L87: 4 | M87: 791600 | N87: 3166400 | O87: 2216480 | P87: 2025-04-10 | Q87: 2027-04-08 | R87: 12 | S87: Price negotiation | T87: Distributor | V87: =IF(S87="",1,0) | W87: =IF(J87="",1,0) | X87: =IF(F87="",1,0) | Y87: =IF(AND(AND(H87<>"Mass production",H87<>"Lost"),DATEVALUE(Q87)<DATE(2026,10,20)),1,0) | Z87: =IF(AND(AND(H87<>"Mass production",H87<>"Lost"),R87>30),1,0) | AA87: =IF(COUNTIFS($G$2:$G$247,G87,$F$2:$F$247,F87,$J$2:$J$247,J87,$K$2:$K$247,K87)>1,1,0) | AB87: =SUM(V87:AA87)
A88: OPP-26086 | B88: Quorra Electronics | C88: DACH | D88: Austria | E88: L. Hoffmann | F88: Asset tracking | G88: Wi-Fi / Bluetooth | H88: Mass production | I88: 1 | J88: 80000 | K88: 4.43 | L88: 3 | M88: 354400 | N88: 1063200 | O88: 1063200 | P88: 2026-05-21 | Q88: 2026-10-03 | R88: 14 | S88: Quote revision | T88: Direct | V88: =IF(S88="",1,0) | W88: =IF(J88="",1,0) | X88: =IF(F88="",1,0) | Y88: =IF(AND(AND(H88<>"Mass production",H88<>"Lost"),DATEVALUE(Q88)<DATE(2026,10,20)),1,0) | Z88: =IF(AND(AND(H88<>"Mass production",H88<>"Lost"),R88>30),1,0) | AA88: =IF(COUNTIFS($G$2:$G$247,G88,$F$2:$F$247,F88,$J$2:$J$247,J88,$K$2:$K$247,K88)>1,1,0) | AB88: =SUM(V88:AA88)
A89: OPP-26087 | B89: Zenit Industrial | C89: Middle East & Africa | D89: UAE | E89: Y. Cohen | F89: Asset tracking | G89: GNSS | H89: Lost | I89: 0 | J89: 3000 | K89: 8.42 | L89: 3 | M89: 25260 | N89: 75780 | O89: 0 | P89: 2026-03-13 | Q89: 2026-10-11 | R89: 2 | S89: Quote revision | T89: Tradeshow | U89: Technical fit | V89: =IF(S89="",1,0) | W89: =IF(J89="",1,0) | X89: =IF(F89="",1,0) | Y89: =IF(AND(AND(H89<>"Mass production",H89<>"Lost"),DATEVALUE(Q89)<DATE(2026,10,20)),1,0) | Z89: =IF(AND(AND(H89<>"Mass production",H89<>"Lost"),R89>30),1,0) | AA89: =IF(COUNTIFS($G$2:$G$247,G89,$F$2:$F$247,F89,$J$2:$J$247,J89,$K$2:$K$247,K89)>1,1,0) | AB89: =SUM(V89:AA89)
A90: OPP-26088 | B90: Bluecell Labs | C90: Southern Europe | D90: Portugal | E90: A. Garcia | F90: POS & payments | G90: Wi-Fi / Bluetooth | H90: Lead | I90: 0.05 | J90: 2000 | K90: 2.6 | L90: 5 | M90: 5200 | N90: 26000 | O90: 1300 | P90: 2026-01-02 | Q90: 2027-08-09 | R90: 28 | S90: Pilot build follow-up | T90: Distributor | V90: =IF(S90="",1,0) | W90: =IF(J90="",1,0) | X90: =IF(F90="",1,0) | Y90: =IF(AND(AND(H90<>"Mass production",H90<>"Lost"),DATEVALUE(Q90)<DATE(2026,10,20)),1,0) | Z90: =IF(AND(AND(H90<>"Mass production",H90<>"Lost"),R90>30),1,0) | AA90: =IF(COUNTIFS($G$2:$G$247,G90,$F$2:$F$247,F90,$J$2:$J$247,J90,$K$2:$K$247,K90)>1,1,0) | AB90: =SUM(V90:AA90)
A91: OPP-26089 | B91: Ferro Energy | C91: France & Benelux | D91: Belgium | E91: C. Martin | F91: Healthcare | G91: LTE-M / NB-IoT | H91: Sample / Evaluation | I91: 0.2 | J91: 2000 | K91: 5.72 | L91: 3 | M91: 11440 | N91: 34320 | O91: 6864 | P91: 2025-07-07 | Q91: 2027-04-10 | R91: 7 | S91: Forecast confirmation | T91: Tradeshow | V91: =IF(S91="",1,0) | W91: =IF(J91="",1,0) | X91: =IF(F91="",1,0) | Y91: =IF(AND(AND(H91<>"Mass production",H91<>"Lost"),DATEVALUE(Q91)<DATE(2026,10,20)),1,0) | Z91: =IF(AND(AND(H91<>"Mass production",H91<>"Lost"),R91>30),1,0) | AA91: =IF(COUNTIFS($G$2:$G$247,G91,$F$2:$F$247,F91,$J$2:$J$247,J91,$K$2:$K$247,K91)>1,1,0) | AB91: =SUM(V91:AA91)
A92: OPP-26090 | B92: Alpenlink Electronics | C92: DACH | D92: Germany | E92: J. Weber | F92: Smart metering | G92: LTE Cat 1 bis | H92: Qualified | I92: 0.1 | J92: 3000 | K92: 9.3 | L92: 3 | M92: 27900 | N92: 83700 | O92: 8370 | P92: 2026-01-26 | Q92: 2027-05-06 | R92: 1 | S92: Pilot build follow-up | T92: FAE referral | V92: =IF(S92="",1,0) | W92: =IF(J92="",1,0) | X92: =IF(F92="",1,0) | Y92: =IF(AND(AND(H92<>"Mass production",H92<>"Lost"),DATEVALUE(Q92)<DATE(2026,10,20)),1,0) | Z92: =IF(AND(AND(H92<>"Mass production",H92<>"Lost"),R92>30),1,0) | AA92: =IF(COUNTIFS($G$2:$G$247,G92,$F$2:$F$247,F92,$J$2:$J$247,J92,$K$2:$K$247,K92)>1,1,0) | AB92: =SUM(V92:AA92)
A93: OPP-26091 | B93: Stellar Energy | C93: Middle East & Africa | D93: South Africa | E93: O. Demir | F93: Telematics | G93: Wi-Fi / Bluetooth | H93: Sample / Evaluation | I93: 0.2 | K93: 5.66 | L93: 5 | M93: 0 | N93: 0 | O93: 0 | P93: 2025-11-14 | Q93: 2026-12-16 | R93: 94 | S93: Pilot build follow-up | T93: Distributor | V93: =IF(S93="",1,0) | W93: =IF(J93="",1,0) | X93: =IF(F93="",1,0) | Y93: =IF(AND(AND(H93<>"Mass production",H93<>"Lost"),DATEVALUE(Q93)<DATE(2026,10,20)),1,0) | Z93: =IF(AND(AND(H93<>"Mass production",H93<>"Lost"),R93>30),1,0) | AA93: =IF(COUNTIFS($G$2:$G$247,G93,$F$2:$F$247,F93,$J$2:$J$247,J93,$K$2:$K$247,K93)>1,1,0) | AB93: =SUM(V93:AA93)
A94: OPP-26092 | B94: Nordwind Telematics | C94: Nordics | D94: Sweden | E94: E. Lindqvist | F94: Smart home & security | G94: 5G eMBB | H94: Design-in | I94: 0.4 | J94: 15000 | K94: 96.83 | L94: 2 | M94: 1452450 | N94: 2904900 | O94: 1161960 | P94: 2026-08-10 | Q94: 2027-02-01 | R94: 7 | S94: Quote revision | T94: FAE referral | V94: =IF(S94="",1,0) | W94: =IF(J94="",1,0) | X94: =IF(F94="",1,0) | Y94: =IF(AND(AND(H94<>"Mass production",H94<>"Lost"),DATEVALUE(Q94)<DATE(2026,10,20)),1,0) | Z94: =IF(AND(AND(H94<>"Mass production",H94<>"Lost"),R94>30),1,0) | AA94: =IF(COUNTIFS($G$2:$G$247,G94,$F$2:$F$247,F94,$J$2:$J$247,J94,$K$2:$K$247,K94)>1,1,0) | AB94: =SUM(V94:AA94)
A95: OPP-26093 | B95: Alpenlink Electronics | C95: DACH | D95: Germany | E95: L. Hoffmann | F95: Automotive & C-V2X | G95: LTE-M / NB-IoT | H95: Sample / Evaluation | I95: 0.2 | J95: 50000 | K95: 5.65 | L95: 3 | M95: 282500 | N95: 847500 | O95: 169500 | P95: 2025-09-24 | Q95: 2027-06-20 | R95: 4 | S95: Quote revision | T95: FAE referral | V95: =IF(S95="",1,0) | W95: =IF(J95="",1,0) | X95: =IF(F95="",1,0) | Y95: =IF(AND(AND(H95<>"Mass production",H95<>"Lost"),DATEVALUE(Q95)<DATE(2026,10,20)),1,0) | Z95: =IF(AND(AND(H95<>"Mass production",H95<>"Lost"),R95>30),1,0) | AA95: =IF(COUNTIFS($G$2:$G$247,G95,$F$2:$F$247,F95,$J$2:$J$247,J95,$K$2:$K$247,K95)>1,1,0) | AB95: =SUM(V95:AA95)
A96: OPP-26094 | B96: Rhenus Health | C96: Nordics | D96: Finland | E96: E. Lindqvist | F96: Telematics | G96: LTE Cat 1 bis | H96: Design-in | I96: 0.4 | J96: 8000 | K96: 10.14 | L96: 5 | M96: 81120 | N96: 405600 | O96: 162240 | P96: 2025-04-27 | Q96: 2027-04-03 | R96: 8 | S96: Price negotiation | T96: Direct | V96: =IF(S96="",1,0) | W96: =IF(J96="",1,0) | X96: =IF(F96="",1,0) | Y96: =IF(AND(AND(H96<>"Mass production",H96<>"Lost"),DATEVALUE(Q96)<DATE(2026,10,20)),1,0) | Z96: =IF(AND(AND(H96<>"Mass production",H96<>"Lost"),R96>30),1,0) | AA96: =IF(COUNTIFS($G$2:$G$247,G96,$F$2:$F$247,F96,$J$2:$J$247,J96,$K$2:$K$247,K96)>1,1,0) | AB96: =SUM(V96:AA96)
A97: OPP-26095 | B97: Helix Tracking | C97: UK & Ireland | D97: United Kingdom | E97: S. Clarke | F97: Healthcare | G97: GNSS | H97: Sample / Evaluation | I97: 0.2 | J97: 20000 | K97: 5.25 | L97: 5 | M97: 105000 | N97: 525000 | O97: 105000 | P97: 2025-11-28 | Q97: 2027-07-10 | R97: 5 | S97: Forecast confirmation | T97: Tradeshow | V97: =IF(S97="",1,0) | W97: =IF(J97="",1,0) | X97: =IF(F97="",1,0) | Y97: =IF(AND(AND(H97<>"Mass production",H97<>"Lost"),DATEVALUE(Q97)<DATE(2026,10,20)),1,0) | Z97: =IF(AND(AND(H97<>"Mass production",H97<>"Lost"),R97>30),1,0) | AA97: =IF(COUNTIFS($G$2:$G$247,G97,$F$2:$F$247,F97,$J$2:$J$247,J97,$K$2:$K$247,K97)>1,1,0) | AB97: =SUM(V97:AA97)
A98: OPP-26096 | B98: Vector Devices | C98: UK & Ireland | D98: United Kingdom | E98: S. Clarke | F98: Smart home & security | G98: Smart module | H98: Sample / Evaluation | I98: 0.2 | J98: 2000 | K98: 88.6 | L98: 5 | M98: 177200 | N98: 886000 | O98: 177200 | P98: 2025-06-02 | Q98: 2027-01-23 | R98: 10 | S98: Quote revision | T98: Website | V98: =IF(S98="",1,0) | W98: =IF(J98="",1,0) | X98: =IF(F98="",1,0) | Y98: =IF(AND(AND(H98<>"Mass production",H98<>"Lost"),DATEVALUE(Q98)<DATE(2026,10,20)),1,0) | Z98: =IF(AND(AND(H98<>"Mass production",H98<>"Lost"),R98>30),1,0) | AA98: =IF(COUNTIFS($G$2:$G$247,G98,$F$2:$F$247,F98,$J$2:$J$247,J98,$K$2:$K$247,K98)>1,1,0) | AB98: =SUM(V98:AA98)
A99: OPP-26097 | B99: Iberix Electronics | C99: Middle East & Africa | D99: UAE | E99: O. Demir | F99: Smart metering | G99: 5G RedCap | H99: Lost | I99: 0 | J99: 30000 | K99: 42.58 | L99: 3 | M99: 1277400 | N99: 3832200 | O99: 0 | P99: 2025-07-29 | Q99: 2026-02-11 | R99: 11 | S99: Quote revision | T99: Distributor | U99: Technical fit | V99: =IF(S99="",1,0) | W99: =IF(J99="",1,0) | X99: =IF(F99="",1,0) | Y99: =IF(AND(AND(H99<>"Mass production",H99<>"Lost"),DATEVALUE(Q99)<DATE(2026,10,20)),1,0) | Z99: =IF(AND(AND(H99<>"Mass production",H99<>"Lost"),R99>30),1,0) | AA99: =IF(COUNTIFS($G$2:$G$247,G99,$F$2:$F$247,F99,$J$2:$J$247,J99,$K$2:$K$247,K99)>1,1,0) | AB99: =SUM(V99:AA99)
A100: OPP-26098 | B100: Quorra Mobility | C100: France & Benelux | D100: Netherlands | E100: B. de Vries | F100: Telematics | G100: LTE-M / NB-IoT | H100: Design-in | I100: 0.4 | J100: 5000 | K100: 6.44 | L100: 4 | M100: 32200 | N100: 128800 | O100: 51520 | P100: 2025-04-03 | Q100: 2027-03-04 | R100: 26 | S100: Certification plan | T100: FAE referral | V100: =IF(S100="",1,0) | W100: =IF(J100="",1,0) | X100: =IF(F100="",1,0) | Y100: =IF(AND(AND(H100<>"Mass production",H100<>"Lost"),DATEVALUE(Q100)<DATE(2026,10,20)),1,0) | Z100: =IF(AND(AND(H100<>"Mass production",H100<>"Lost"),R100>30),1,0) | AA100: =IF(COUNTIFS($G$2:$G$247,G100,$F$2:$F$247,F100,$J$2:$J$247,J100,$K$2:$K$247,K100)>1,1,0) | AB100: =SUM(V100:AA100)
...

Sheet Pipeline summary
A1: Lifetime value (USD) by stage and region
A2: Stage | B2: DACH | C2: UK & Ireland | D2: France & Benelux | E2: Southern Europe | F2: Nordics | G2: CEE | H2: Middle East & Africa | I2: Total
A3: Lead | B3: =SUMIFS(Opportunities!$N$2:$N$247,Opportunities!$H$2:$H$247,$A3,Opportunities!$C$2:$C$247,B$2) | C3: =SUMIFS(Opportunities!$N$2:$N$247,Opportunities!$H$2:$H$247,$A3,Opportunities!$C$2:$C$247,C$2) | D3: =SUMIFS(Opportunities!$N$2:$N$247,Opportunities!$H$2:$H$247,$A3,Opportunities!$C$2:$C$247,D$2) | E3: =SUMIFS(Opportunities!$N$2:$N$247,Opportunities!$H$2:$H$247,$A3,Opportunities!$C$2:$C$247,E$2) | F3: =SUMIFS(Opportunities!$N$2:$N$247,Opportunities!$H$2:$H$247,$A3,Opportunities!$C$2:$C$247,F$2) | G3: =SUMIFS(Opportunities!$N$2:$N$247,Opportunities!$H$2:$H$247,$A3,Opportunities!$C$2:$C$247,G$2) | H3: =SUMIFS(Opportunities!$N$2:$N$247,Opportunities!$H$2:$H$247,$A3,Opportunities!$C$2:$C$247,H$2) | I3: =SUM(B3:H3)
A4: Qualified | B4: =SUMIFS(Opportunities!$N$2:$N$247,Opportunities!$H$2:$H$247,$A4,Opportunities!$C$2:$C$247,B$2) | C4: =SUMIFS(Opportunities!$N$2:$N$247,Opportunities!$H$2:$H$247,$A4,Opportunities!$C$2:$C$247,C$2) | D4: =SUMIFS(Opportunities!$N$2:$N$247,Opportunities!$H$2:$H$247,$A4,Opportunities!$C$2:$C$247,D$2) | E4: =SUMIFS(Opportunities!$N$2:$N$247,Opportunities!$H$2:$H$247,$A4,Opportunities!$C$2:$C$247,E$2) | F4: =SUMIFS(Opportunities!$N$2:$N$247,Opportunities!$H$2:$H$247,$A4,Opportunities!$C$2:$C$247,F$2) | G4: =SUMIFS(Opportunities!$N$2:$N$247,Opportunities!$H$2:$H$247,$A4,Opportunities!$C$2:$C$247,G$2) | H4: =SUMIFS(Opportunities!$N$2:$N$247,Opportunities!$H$2:$H$247,$A4,Opportunities!$C$2:$C$247,H$2) | I4: =SUM(B4:H4)
A5: Sample / Evaluation | B5: =SUMIFS(Opportunities!$N$2:$N$247,Opportunities!$H$2:$H$247,$A5,Opportunities!$C$2:$C$247,B$2) | C5: =SUMIFS(Opportunities!$N$2:$N$247,Opportunities!$H$2:$H$247,$A5,Opportunities!$C$2:$C$247,C$2) | D5: =SUMIFS(Opportunities!$N$2:$N$247,Opportunities!$H$2:$H$247,$A5,Opportunities!$C$2:$C$247,D$2) | E5: =SUMIFS(Opportunities!$N$2:$N$247,Opportunities!$H$2:$H$247,$A5,Opportunities!$C$2:$C$247,E$2) | F5: =SUMIFS(Opportunities!$N$2:$N$247,Opportunities!$H$2:$H$247,$A5,Opportunities!$C$2:$C$247,F$2) | G5: =SUMIFS(Opportunities!$N$2:$N$247,Opportunities!$H$2:$H$247,$A5,Opportunities!$C$2:$C$247,G$2) | H5: =SUMIFS(Opportunities!$N$2:$N$247,Opportunities!$H$2:$H$247,$A5,Opportunities!$C$2:$C$247,H$2) | I5: =SUM(B5:H5)
A6: Design-in | B6: =SUMIFS(Opportunities!$N$2:$N$247,Opportunities!$H$2:$H$247,$A6,Opportunities!$C$2:$C$247,B$2) | C6: =SUMIFS(Opportunities!$N$2:$N$247,Opportunities!$H$2:$H$247,$A6,Opportunities!$C$2:$C$247,C$2) | D6: =SUMIFS(Opportunities!$N$2:$N$247,Opportunities!$H$2:$H$247,$A6,Opportunities!$C$2:$C$247,D$2) | E6: =SUMIFS(Opportunities!$N$2:$N$247,Opportunities!$H$2:$H$247,$A6,Opportunities!$C$2:$C$247,E$2) | F6: =SUMIFS(Opportunities!$N$2:$N$247,Opportunities!$H$2:$H$247,$A6,Opportunities!$C$2:$C$247,F$2) | G6: =SUMIFS(Opportunities!$N$2:$N$247,Opportunities!$H$2:$H$247,$A6,Opportunities!$C$2:$C$247,G$2) | H6: =SUMIFS(Opportunities!$N$2:$N$247,Opportunities!$H$2:$H$247,$A6,Opportunities!$C$2:$C$247,H$2) | I6: =SUM(B6:H6)
A7: Design-win | B7: =SUMIFS(Opportunities!$N$2:$N$247,Opportunities!$H$2:$H$247,$A7,Opportunities!$C$2:$C$247,B$2) | C7: =SUMIFS(Opportunities!$N$2:$N$247,Opportunities!$H$2:$H$247,$A7,Opportunities!$C$2:$C$247,C$2) | D7: =SUMIFS(Opportunities!$N$2:$N$247,Opportunities!$H$2:$H$247,$A7,Opportunities!$C$2:$C$247,D$2) | E7: =SUMIFS(Opportunities!$N$2:$N$247,Opportunities!$H$2:$H$247,$A7,Opportunities!$C$2:$C$247,E$2) | F7: =SUMIFS(Opportunities!$N$2:$N$247,Opportunities!$H$2:$H$247,$A7,Opportunities!$C$2:$C$247,F$2) | G7: =SUMIFS(Opportunities!$N$2:$N$247,Opportunities!$H$2:$H$247,$A7,Opportunities!$C$2:$C$247,G$2) | H7: =SUMIFS(Opportunities!$N$2:$N$247,Opportunities!$H$2:$H$247,$A7,Opportunities!$C$2:$C$247,H$2) | I7: =SUM(B7:H7)
A8: Pilot | B8: =SUMIFS(Opportunities!$N$2:$N$247,Opportunities!$H$2:$H$247,$A8,Opportunities!$C$2:$C$247,B$2) | C8: =SUMIFS(Opportunities!$N$2:$N$247,Opportunities!$H$2:$H$247,$A8,Opportunities!$C$2:$C$247,C$2) | D8: =SUMIFS(Opportunities!$N$2:$N$247,Opportunities!$H$2:$H$247,$A8,Opportunities!$C$2:$C$247,D$2) | E8: =SUMIFS(Opportunities!$N$2:$N$247,Opportunities!$H$2:$H$247,$A8,Opportunities!$C$2:$C$247,E$2) | F8: =SUMIFS(Opportunities!$N$2:$N$247,Opportunities!$H$2:$H$247,$A8,Opportunities!$C$2:$C$247,F$2) | G8: =SUMIFS(Opportunities!$N$2:$N$247,Opportunities!$H$2:$H$247,$A8,Opportunities!$C$2:$C$247,G$2) | H8: =SUMIFS(Opportunities!$N$2:$N$247,Opportunities!$H$2:$H$247,$A8,Opportunities!$C$2:$C$247,H$2) | I8: =SUM(B8:H8)
A9: Mass production | B9: =SUMIFS(Opportunities!$N$2:$N$247,Opportunities!$H$2:$H$247,$A9,Opportunities!$C$2:$C$247,B$2) | C9: =SUMIFS(Opportunities!$N$2:$N$247,Opportunities!$H$2:$H$247,$A9,Opportunities!$C$2:$C$247,C$2) | D9: =SUMIFS(Opportunities!$N$2:$N$247,Opportunities!$H$2:$H$247,$A9,Opportunities!$C$2:$C$247,D$2) | E9: =SUMIFS(Opportunities!$N$2:$N$247,Opportunities!$H$2:$H$247,$A9,Opportunities!$C$2:$C$247,E$2) | F9: =SUMIFS(Opportunities!$N$2:$N$247,Opportunities!$H$2:$H$247,$A9,Opportunities!$C$2:$C$247,F$2) | G9: =SUMIFS(Opportunities!$N$2:$N$247,Opportunities!$H$2:$H$247,$A9,Opportunities!$C$2:$C$247,G$2) | H9: =SUMIFS(Opportunities!$N$2:$N$247,Opportunities!$H$2:$H$247,$A9,Opportunities!$C$2:$C$247,H$2) | I9: =SUM(B9:H9)
A10: Lost | B10: =SUMIFS(Opportunities!$N$2:$N$247,Opportunities!$H$2:$H$247,$A10,Opportunities!$C$2:$C$247,B$2) | C10: =SUMIFS(Opportunities!$N$2:$N$247,Opportunities!$H$2:$H$247,$A10,Opportunities!$C$2:$C$247,C$2) | D10: =SUMIFS(Opportunities!$N$2:$N$247,Opportunities!$H$2:$H$247,$A10,Opportunities!$C$2:$C$247,D$2) | E10: =SUMIFS(Opportunities!$N$2:$N$247,Opportunities!$H$2:$H$247,$A10,Opportunities!$C$2:$C$247,E$2) | F10: =SUMIFS(Opportunities!$N$2:$N$247,Opportunities!$H$2:$H$247,$A10,Opportunities!$C$2:$C$247,F$2) | G10: =SUMIFS(Opportunities!$N$2:$N$247,Opportunities!$H$2:$H$247,$A10,Opportunities!$C$2:$C$247,G$2) | H10: =SUMIFS(Opportunities!$N$2:$N$247,Opportunities!$H$2:$H$247,$A10,Opportunities!$C$2:$C$247,H$2) | I10: =SUM(B10:H10)

Sheet Data quality
A1: Region | B1: Records | C1: Records with issues | D1: Completeness % | E1: Stale open | F1: Close date in past | G1: Possible duplicates
A2: DACH | B2: =COUNTIF(Opportunities!$C$2:$C$247,A2) | C2: =COUNTIFS(Opportunities!$C$2:$C$247,A2,Opportunities!$AB$2:$AB$247,">0") | D2: =IF(B2=0,0,1-C2/B2) | E2: =SUMIFS(Opportunities!$Z$2:$Z$247,Opportunities!$C$2:$C$247,A2) | F2: =SUMIFS(Opportunities!$Y$2:$Y$247,Opportunities!$C$2:$C$247,A2) | G2: =SUMIFS(Opportunities!$AA$2:$AA$247,Opportunities!$C$2:$C$247,A2)
A3: UK & Ireland | B3: =COUNTIF(Opportunities!$C$2:$C$247,A3) | C3: =COUNTIFS(Opportunities!$C$2:$C$247,A3,Opportunities!$AB$2:$AB$247,">0") | D3: =IF(B3=0,0,1-C3/B3) | E3: =SUMIFS(Opportunities!$Z$2:$Z$247,Opportunities!$C$2:$C$247,A3) | F3: =SUMIFS(Opportunities!$Y$2:$Y$247,Opportunities!$C$2:$C$247,A3) | G3: =SUMIFS(Opportunities!$AA$2:$AA$247,Opportunities!$C$2:$C$247,A3)
A4: France & Benelux | B4: =COUNTIF(Opportunities!$C$2:$C$247,A4) | C4: =COUNTIFS(Opportunities!$C$2:$C$247,A4,Opportunities!$AB$2:$AB$247,">0") | D4: =IF(B4=0,0,1-C4/B4) | E4: =SUMIFS(Opportunities!$Z$2:$Z$247,Opportunities!$C$2:$C$247,A4) | F4: =SUMIFS(Opportunities!$Y$2:$Y$247,Opportunities!$C$2:$C$247,A4) | G4: =SUMIFS(Opportunities!$AA$2:$AA$247,Opportunities!$C$2:$C$247,A4)
A5: Southern Europe | B5: =COUNTIF(Opportunities!$C$2:$C$247,A5) | C5: =COUNTIFS(Opportunities!$C$2:$C$247,A5,Opportunities!$AB$2:$AB$247,">0") | D5: =IF(B5=0,0,1-C5/B5) | E5: =SUMIFS(Opportunities!$Z$2:$Z$247,Opportunities!$C$2:$C$247,A5) | F5: =SUMIFS(Opportunities!$Y$2:$Y$247,Opportunities!$C$2:$C$247,A5) | G5: =SUMIFS(Opportunities!$AA$2:$AA$247,Opportunities!$C$2:$C$247,A5)
A6: Nordics | B6: =COUNTIF(Opportunities!$C$2:$C$247,A6) | C6: =COUNTIFS(Opportunities!$C$2:$C$247,A6,Opportunities!$AB$2:$AB$247,">0") | D6: =IF(B6=0,0,1-C6/B6) | E6: =SUMIFS(Opportunities!$Z$2:$Z$247,Opportunities!$C$2:$C$247,A6) | F6: =SUMIFS(Opportunities!$Y$2:$Y$247,Opportunities!$C$2:$C$247,A6) | G6: =SUMIFS(Opportunities!$AA$2:$AA$247,Opportunities!$C$2:$C$247,A6)
A7: CEE | B7: =COUNTIF(Opportunities!$C$2:$C$247,A7) | C7: =COUNTIFS(Opportunities!$C$2:$C$247,A7,Opportunities!$AB$2:$AB$247,">0") | D7: =IF(B7=0,0,1-C7/B7) | E7: =SUMIFS(Opportunities!$Z$2:$Z$247,Opportunities!$C$2:$C$247,A7) | F7: =SUMIFS(Opportunities!$Y$2:$Y$247,Opportunities!$C$2:$C$247,A7) | G7: =SUMIFS(Opportunities!$AA$2:$AA$247,Opportunities!$C$2:$C$247,A7)
A8: Middle East & Africa | B8: =COUNTIF(Opportunities!$C$2:$C$247,A8) | C8: =COUNTIFS(Opportunities!$C$2:$C$247,A8,Opportunities!$AB$2:$AB$247,">0") | D8: =IF(B8=0,0,1-C8/B8) | E8: =SUMIFS(Opportunities!$Z$2:$Z$247,Opportunities!$C$2:$C$247,A8) | F8: =SUMIFS(Opportunities!$Y$2:$Y$247,Opportunities!$C$2:$C$247,A8) | G8: =SUMIFS(Opportunities!$AA$2:$AA$247,Opportunities!$C$2:$C$247,A8)

Sheet Forecast
A1: Quarter | B1: Forecast (M USD) | C1: Actual (M USD) | D1: Variance | E1: Accuracy %
A2: Q3 25 | B2: 8.2 | C2: 7.4 | D2: =IF(C2="","",C2-B2) | E2: =IF(C2="","",1-ABS(C2-B2)/B2)
A3: Q4 25 | B3: 8.9 | C3: 9.2 | D3: =IF(C3="","",C3-B3) | E3: =IF(C3="","",1-ABS(C3-B3)/B3)
A4: Q1 26 | B4: 9.4 | C4: 8.3 | D4: =IF(C4="","",C4-B4) | E4: =IF(C4="","",1-ABS(C4-B4)/B4)
A5: Q2 26 | B5: 9.9 | C5: 9.6 | D5: =IF(C5="","",C5-B5) | E5: =IF(C5="","",1-ABS(C5-B5)/B5)
A6: Q3 26 | B6: 10.6 | C6: 10.3 | D6: =IF(C6="","",C6-B6) | E6: =IF(C6="","",1-ABS(C6-B6)/B6)
A7: Q4 26 | B7: 11.2 | D7: =IF(C7="","",C7-B7) | E7: =IF(C7="","",1-ABS(C7-B7)/B7)

Sheet Tradeshows
A1: Event | B1: City | C1: Month | D1: Cost (EUR) | E1: Meetings | F1: Leads | G1: Qualified | H1: Opportunities | I1: Pipeline (EUR) | J1: Lead to qualified % | K1: Cost per qualified lead | L1: Pipeline per EUR
A2: Embedded World | B2: Nuremberg | C2: Mar 2026 | D2: 92000 | E2: 148 | F2: 412 | G2: 131 | H2: 38 | I2: 9400000 | J2: =IF(F2="","",G2/F2) | K2: =IF(G2="","",D2/G2) | L2: =IF(I2="","",I2/D2)
A3: MWC | B3: Barcelona | C3: Mar 2026 | D3: 118000 | E3: 96 | F3: 265 | G3: 70 | H3: 17 | I3: 6100000 | J3: =IF(F3="","",G3/F3) | K3: =IF(G3="","",D3/G3) | L3: =IF(I3="","",I3/D3)
A4: Hannover Messe | B4: Hannover | C4: Apr 2026 | D4: 54000 | E4: 61 | F4: 188 | G4: 49 | H4: 14 | I4: 3300000 | J4: =IF(F4="","",G4/F4) | K4: =IF(G4="","",D4/G4) | L4: =IF(I4="","",I4/D4)
A5: IoT Tech Expo Europe | B5: Amsterdam | C5: Sep 2026 | D5: 31000 | E5: 44 | F5: 156 | G5: 38 | H5: 9 | I5: 1700000 | J5: =IF(F5="","",G5/F5) | K5: =IF(G5="","",D5/G5) | L5: =IF(I5="","",I5/D5)
A6: electronica | B6: Munich | C6: Nov 2026 | D6: 86000 | J6: =IF(F6="","",G6/F6) | K6: =IF(G6="","",D6/G6) | L6: =IF(I6="","",I6/D6)
